Workbook

Sheet Schedule
A1: Job # | B1: Job Name | C1: GC | D1: Units | E1: Project Start Date | F1: RI Foreman | G1: Trim Foreman | H1: Address | I1: 41913 | J1: 42767 | K1: 41944 | M1: 41974 | N1: 42856 | O1: 42005 | P1: 42767 | Q1: 42036 | S1: 42064 | T1: 42856 | U1: 42095 | V1: 42125 | W1: 42156 | X1: 42186 | Z1: 42217 | AB1: 42248 | AD1: 42278 | AF1: 42309 | AH1: 42339 | AJ1: 42370 | AL1: 42401 | AN1: 42430 | AP1: 42461 | AR1: 42491 | AT1: 42522 | AU1: 42552 | AV1: 42552 | AW1: 42614 | AX1: 42583 | AZ1: 42614 | BA1: 42705 | BB1: 42644 | BC1: 42767 | BD1: 42675 | BF1: 42705 | BG1: 42856 | BH1: 42736 | BI1: 42917 | BJ1: 42767 | BL1: 42795 | BM1: 43009 | BN1: 42826 | BO1: 43070 | BP1: 42856 | BR1: 42887 | BS1: 43160 | BT1: 42917 | BU1: 43221 | BV1: 42948 | BX1: 42979 | BY1: 43313 | BZ1: 43009 | CA1: 43374 | CB1: 43040 | CC1: 43070 | CD1: 43070 | CF1: 43101 | CH1: 43132 | CJ1: 43160 | CL1: 43191 | CN1: 43221 | CP1: 43252 | CR1: 43282 | CT1: 43313 | CV1: 43344 | CX1: 43374 | CZ1: 43405 | DB1: 43435 | DD1: 43466 | DF1: 43497 | DH1: 43525 | DJ1: 43556 | DL1: 43586 | DN1: 43617 | DP1: 43647 | DR1: 43678 | DT1: 43709 | DV1: 43739 | DX1: 43770 | DZ1: 43800 | EB1: 43831 | ED1: 43862 | EF1: 43891 | EH1: 43922 | EJ1: 43952 | EL1: 43983 | EN1: 44013 | EP1: 44044 | ER1: 44075 | ET1: 44105 | EV1: 44136 | EX1: 44166 | EZ1: 44197 | FB1: 44228 | FD1: 44256 | FF1: 44287 | FH1: 44317 | FJ1: 44348 | FL1: 44378 | FN1: 44409 | FP1: 44440 | FR1: 44470 | FT1: 44501 | FV1: 44531 | FX1: 44562 | FZ1: 44593 | GB1: 44621 | GD1: 44652 | GF1: 44682 | GH1: 44713 | GJ1: 44743 | GL1: 44774 | GN1: 44805 | GP1: 44835 | GR1: 44866 | GT1: 44896 | GV1: 44927 | GX1: 44958 | GZ1: 44986 | HB1: 45017 | HD1: 45047 | HF1: 45078 | HH1: 45108 | HJ1: 45139 | HL1: 45170 | HN1: 45200 | HP1: 45231 | HR1: 45261 | HT1: 45292 | HV1: 45323 | HX1: 45352 | HZ1: 45383 | IB1: 45413 | ID1: 45444 | IF1: 45474 | IH1: 45505 | IJ1: 45536 | IL1: 45566 | IN1: 45597 | IP1: 45627 | IR1: 45658 | IT1: 45689 | IV1: 45717 | IX1: 45748 | IZ1: 45778 | JB1: 45809 | JD1: 45839 | JF1: 45870 | JH1: 45901 | JJ1: 45931 | JL1: 45962 | JN1: 45992 | JP1: 46023 | JR1: 46054 | JT1: 46082 | JV1: 46113 | JX1: 46143 | JZ1: 46174 | KB1: 46204 | KD1: 46235 | KF1: 46266 | KH1: 46296 | KJ1: 46327 | KL1: 46357 | KN1: 46388 | KP1: 46419 | KR1: 46447 | KT1: 46478 | KV1: 46508 | KX1: 46539 | KZ1: 46569 | LB1: 46600
A2: 2001 | B2: 230 Broadway | C2: SRM | D2: 234
A3: 2002 | B3: Wedgewood | C3: Exxel Pacific | D3: 91
A4: 2003 | B4: Evanston Space | C4: Exxel Pacific | D4: 28
A5: 2005 | B5: Indigo/Kavela | C5: Chinn | D5: 66
A6: 2006 | B6: Bella Lago | C6: ICC | D6: 319
A7: 2008 | B7: 101 Taylor | C7: SRM | D7: 258 | F7: Bob | G7: Al
A8: 2009 | B8: Greenwood | C8: Chinn | D8: 56
A9: 2010 | B9: Old Town | C9: Chinn | D9: 149
A10: 2011 | B10: Barrett Park | C10: Chinn | D10: 117
A11: 2012 | B11: 8th Ave | C11: Exxel Pacific | D11: 162
A12: 2013 | B12: NE 63rd | C12: Exxel Pacific | D12: 112
A13: 2016 | B13: Sedona | C13: Natural & Built | D13: 85
A14: 2018 | B14: Astro | C14: SRM | D14: 211 | F14: Bob | G14: Al | I14: TRIM | K14: TRIM | M14: TRIM | O14: TRIM | Q14: TRIM | S14: TRIM
A15: 2017 | B15: 36 Stone | C15: Exxel Pacific | D15: 119 | F15: Esteban | G15: Al | I15: RI | K15: RI | M15: TRIM | O15: TRIM | Q15: TRIM | S15: TRIM
A16: 2022 | B16: Interlake | C16: Exxel Pacific | D16: 18 | F16: Al | G16: Al | M16: GW | O16: GW | S16: RI | U16: RI | W16: TRIM
A17: 2015 | B17: Rooster | C17: Exxel Pacific | D17: 197 | F17: Al - Trim | G17: Al | I17: RI | K17: RI | M17: RI | O17: RI | Q17: RI | S17: RI | U17: RI | V17: RI | W17: TRIM | X17: TRIM | Z17: TRIM | AB17: TRIM
A18: 2014 | B18: Pike Motorworks | C18: Exxel Pacific | D18: 258 | F18: Joe | G18: Joe | H18: 714 E Pike Street, Seattle, WA 98122 | I18: RI | K18: RI | M18: RI | O18: RI | Q18: RI | S18: RI | U18: RI | V18: RI | W18: TRIM | X18: TRIM | Z18: TRIM | AB18: TRIM | AD18: TRIM | AF18: TRIM | AH18: TRIM | AJ18: TRIM
A19: 2020 | B19: Bellevue Main | C19: SRM | D19: 256 | F19: Nate (Al trim) | G19: Al | H19: 15 Bellevue Way SE, Bellevue, WA 98004 | I19: RI | K19: RI | M19: RI | O19: RI | Q19: RI | S19: RI | U19: RI | V19: RI | W19: RI | X19: RI | Z19: RI | AB19: TRIM | AD19: TRIM | AF19: TRIM | AH19: TRIM | AJ19: TRIM | AL19: TRIM
A20: 2019 | B20: 8th Republic | C20: Exxel Pacific | D20: 211 | F20: Thaddeus (Al trim) | G20: Al/Rick | H20: 430 8th Ave North, Seattle, WA 98109 | I20: GW | K20: GW | M20: PT | O20: PT | Q20: PT | S20: PT | U20: RI | V20: RI | W20: RI | X20: RI | Z20: RI | AB20: RI | AD20: TRIM | AF20: TRIM | AH20: TRIM | AJ20: TRIM | AL20: TRIM
A21: 2024 | B21: Merrill Gardens | C21: SRM | D21: 117 | F21: Gustavo | G21: Al | H21: 5601 24th Ave NW, Seattle, WA 98107 | S21: GW | U21: GW | V21: PT | W21: PT | X21: RI | Z21: RI | AB21: RI | AD21: RI | AF21: RI | AH21: RI | AJ21: RI | AL21: RI | AN21: TRIM | AP21: TRIM | AR21: TRIM | AT21: TRIM
A22: 2021 | B22: Admiral | C22: Exxel Pacific | D22: 136 | F22: Esteban | G22: Al | H22: 3210 California Ave SW, Seattle, WA 98116 | S22: GW | U22: GW | V22: GW | W22: GW | X22: PT | Z22: PT | AB22: RI | AD22: RI | AF22: RI | AH22: RI | AJ22: RI | AL22: RI | AN22: RI | AP22: TRIM | AR22: TRIM | AT22: TRIM
A23: 2023 | B23: Hadley | C23: Chinn | D23: 209 | F23: Joe | G23: Al | H23: 2601 76th Ave SE, Mercer Island, WA 98040 | O23: GW | Q23: GW | S23: GW | U23: PT | V23: PT | W23: PT | X23: RI | Z23: RI | AB23: RI | AD23: RI | AF23: RI | AH23: RI | AJ23: RI | AL23: RI | AN23: RI | AP23: TRIM | AR23: TRIM | AT23: TRIM | AV23: TRIM | AX23: TRIM | AZ23: TRIM
A24: 2028 | B24: Reserve @ Lynnwood | C24: Exxel Pacific | D24: 296 | H24: 19815 Scriber Lake Road, Lynnwood, WA 98036 | AO24: GW | AP24: PT | AR24: PT | AS24: RI | AT24: PT | AU24: RI | AV24: RI | AX24: RI | AZ24: RI | BB24: RI | BD24: RI | BF24: RI | BH24: TUBS | BJ24: BURN
A25: 2025 | B25: The Cora | C25: Exxel Pacific | D25: 75 | F25: Thaddeus | H25: 19 W Harrison, Seattle, WA 98119 | AU25: GW | AV25: GW | AX25: PT | AZ25: PT | BB25: PT | BC25: RI | BD25: RI | BF25: RI | BH25: RI | BJ25: RI | BL25: PICKUP | BN25: PICKUP | BP25: TRIM | BR25: TRIM
A26: 2026 | B26: Boren | C26: Synnergy | D26: 49 | F26: Gustavo | H26: 525 Boren Ave N, Seattle, WA 98109 | AR26: GW | AT26: GW | AV26: PT | AX26: PT | AZ26: PT | BA26: RI | BB26: RI | BD26: RI | BF26: RI | BH26: RI | BJ26: RI | BL26: PICKUP | BN26: PICKUP | BP26: TRIM | BR26: TRIM | BT26: TRIM
A27: 2029 | B27: Parsonage | C27: Exxel Pacific | D27: 83 | F27: Rick | H27: 4132 Brooklyn Ave NE, Seattle, WA 98105 | AX27: GW | AZ27: GW | BB27: GW | BC27: PT | BD27: PT | BF27: PT | BG27: RI | BH27: RI | BJ27: RI | BL27: RI | BN27: PICKUP | BP27: TRIM | BR27: TRIM | BT27: TRIM
A28: 2027 | B28: 550 Broadway | C28: Exxel Pacific | D28: 170 | F28: Joe | H28: 550 Broadway, Seattle, WA 98122 | AP28: GW | AR28: GW | AS28: PT | AT28: PT | AV28: PT | AX28: PT | AZ28: PT | BB28: RI | BD28: RI | BF28: RI | BH28: RI | BJ28: RI | BL28: PICKUP | BN28: PICKUP | BP28: TRIM | BR28: TRIM | BT28: TRIM | BV28: TRIM
A29: 2035 | B29: 162 Ten | C29: Natural & Built | D29: 92 | E29: 42598 | F29: Reuben | H29: 16210 NE 80th St, Redmond, WA 98052 | BB29: GW | BD29: GW | BF29: PT | BH29: PT | BJ29: PT | BL29: RI | BN29: RI | BP29: RI | BR29: RI | BT29: RI | BV29: RI | BX29: PICKUP | BZ29: PICKUP | CB29: TRIM | CD29: TRIM | CF29: TRIM | CH29: TRIM
A30: 2034 | B30: Park Lane | C30: Compass | D30: 128 | E30: 42587 | F30: Thaddeus | H30: 207 Park Lane, Kirkland, WA 98033 | BF30: GW | BH30: PT | BJ30: PT | BL30: RI | BN30: RI | BP30: RI | BR30: RI | BT30: RI | BV30: RI | BX30: PICKUP | BZ30: PICKUP | CB30: PICKUP | CD30: TRIM | CF30: TRIM | CH30: TRIM
A31: 2032 | B31: Luna | C31: Blueprint | D31: 71 | E31: 42675 | F31: Rick | H31: 6921 Roosevelt Way NE, Seattle, WA 98115 | BK31: GW | BL31: GW | BN31: GW | BO31: RI | BP31: RI | BR31: RI | BT31: RI | BV31: RI | BX31: RI | BZ31: RI | CB31: RI | CD31: TRIM | CF31: TRIM | CH31: TRIM | CJ31: TRIM | CL31: TRIM | CN31: TRIM
A32: 2036 | B32: Westridge | C32: Exxel Pacific | D32: 31 | E32: 42644 | F32: Gustavo | H32: 512 121st Place NE, Bellevue, WA | BI32: GW | BK32: GW | BM32: GW | BN32: GW | BP32: GW | BR32: GW | BT32: RI | BV32: RI | BX32: RI | BZ32: RI | CB32: RI | CD32: PICKUP | CF32: PICKUP | CH32: TRIM | CJ32: TRIM | CL32: TRIM | CN32: TRIM | CP32: TRIM | CR32: TRIM
A33: 2048 | B33: Ballinger | C33: GRE | D33: 72 | E33: 43025 | F33: Esteban | BZ33: RI | CB33: RI | CD33: RI | CF33: RI | CH33: PICKUP | CJ33: TRIM | CL33: TRIM | CN33: TRIM | CP33: TRIM
A34: 2047 | B34: Greenlake | C34: GRE | D34: 70 | E34: 43025 | F34: Reuben | BZ34: RI | CB34: RI | CD34: RI | CF34: RI | CH34: PICKUP | CJ34: PICKUP | CL34: TRIM | CN34: TRIM | CP34: TRIM
A35: 2033 | B35: Vuecrest | C35: Compass | D35: 139 | E35: 42614 | F35: Victor | H35: 1000 100th Ave NE, Bellevue, WA | BG35: GW | BH35: GW | BJ35: GW | BK35: PT | BL35: PT | BM35: RI | BN35: RI | BP35: RI | BR35: RI | BT35: RI | BV35: RI | BX35: RI | BZ35: RI | CB35: RI | CD35: PICKUP | CF35: PICKUP | CH35: TRIM | CJ35: TRIM | CL35: TRIM | CN35: TRIM | CP35: TRIM | CR35: TRIM
A36: 2030 | B36: East Union | C36: Exxel Pacific | D36: 144 | E36: 42675 | F36: Joe | H36: 2220 E. Union Street, Seattle WA | BL36: GW | BN36: GW | BO36: PT | BP36: PT | BR36: PT | BT36: RI | BV36: RI | BX36: RI | BZ36: RI | CB36: RI | CD36: RI | CF36: RI | CH36: PICKUP | CJ36: PICKUP | CL36: TRIM | CN36: TRIM | CP36: TRIM | CR36: TRIM
A37: 2038 | B37: 2nd & John | C37: Compass | D37: 80 | E37: 42783 | F37: Thaddeus / Joe | H37: 200 2nd Ave West, Seattle, WA | BT37: GW | BV37: GW | BX37: PT | BZ37: PT | CB37: PT | CD37: PT | CE37: RI | CF37: RI | CH37: RI | CJ37: RI | CL37: RI | CN37: RI | CP37: PICKUP | CR37: PICKUP | CT37: TRIM | CV37: TRIM | CX37: TRIM | CZ37: TRIM | DB37: TRIM
A38: 2040 | B38: Roosevelt 65th | C38: Blueprint | D38: 55 | E38: 42795 | F38: Garrett / Joe | H38: 1222 NE 65th Street, Seattle, WA 98115 | BX38: GW | BZ38: PT | CB38: PT | CD38: PT | CE38: RI | CF38: RI | CH38: RI | CJ38: RI | CL38: RI | CN38: RI | CP38: RI | CR38: RI | CT38: PICKUP | CV38: TRIM | CX38: TRIM | CZ38: TRIM | DB38: TRIM
A39: 2037 | B39: University Apartments | C39: Marpac | D39: 122 | E39: 42744 | F39: Rick / Joe | H39: 3025 NE 130th Street, Seattle WA | BT39: GW | BV39: GW | BX39: PT | BZ39: PT | CB39: PT | CD39: PT | CF39: PT | CH39: PT | CJ39: RI | CL39: RI | CN39: RI | CP39: RI | CR39: RI | CT39: PICKUP | CV39: PICKUP | CX39: TRIM | CZ39: TRIM | DB39: TRIM
A40: 2042 | B40: Metro Flats | C40: Shelter Holdings | D40: 75 | E40: AUGUST, 17 | F40: Reuben / Bob | CE40: GW | CF40: PT | CH40: PT | CJ40: RI | CL40: RI | CN40: RI | CP40: RI | CR40: RI | CT40: PICKUP | CV40: TRIM | CX40: TRIM | CZ40: TRIM | DB40: TRIM | DD40: TRIM | DF40: TRIM | DH40: TRIM
A41: 2043 | B41: Aegis Mercer Island | C41: Compass | D41: 89 | E41: 42795 | F41: Victor / Bob | CD41: GW | CF41: GW | CH41: PT | CJ41: RI | CL41: RI | CN41: RI | CP41: RI | CR41: RI | CT41: RI | CV41: PICKUP | CX41: PICKUP | CZ41: TRIM | DB41: TRIM | DD41: TRIM | DF41: TRIM | DH41: TRIM
A42: 2031 | B42: Issaquah Gateway | C42: Exxel Pacific | D42: 398 | E42: 42598 | F42: Esteban / Bob | H42: 2290 Newport Way NW, Issaquah, WA 98027 | BC42: GW | BF42: GW | BH42: GW | BJ42: GW | BK42: RI | BL42: RI | BN42: RI | BP42: RI | BR42: RI | BT42: RI | BV42: RI | BX42: RI | BZ42: RI | CB42: RI | CD42: RI | CF42: RI | CH42: RI | CJ42: RI | CL42: RI | CN42: RI | CP42: RI | CR42: RI | CT42: RI | CV42: PICKUP | CX42: TRIM | CZ42: TRIM | DB42: TRIM | DD42: TRIM | DF42: TRIM | DH42: TRIM | DJ42: TRIM | DL42: TRIM
A43: 2046 | B43: 4218 Roosevelt | C43: Marpac | D43: 110 | E43: end of sept mob | F43: Thaddeus / Joe | CI43: GW | CJ43: GW | CL43: PT | CN43: PT | CP43: PT | CR43: PT | CT43: RI | CV43: RI | CX43: RI | CZ43: RI | DB43: RI | DD43: RI | DF43: PICKUP | DH43: TRIM | DJ43: TRIM | DL43: TRIM | DN43: TRIM
A44: 2050 | B44: 2100 E. Madison | C44: Compass | D44: 50 | E44: Winter 18 | F44: Garrett / Joe | CL44: GW | CN44: GW | CP44: PT | CR44: PT | CT44: PT | CV44: RI | CX44: RI | CZ44: RI | DB44: RI | DD44: RI | DF44: PICKUP | DH44: TRIM | DJ44: TRIM | DL44: TRIM
A45: 2044 | B45: Roosevelt 66th | C45: Blueprint | D45: 78 | E45: 42917 | F45: Anthony / Joe | H45: 836 NE 66th Street, Seattle, WA 98115 | CI45: GW | CJ45: GW | CL45: GW | CN45: PT | CP45: PT | CQ45: RI | CR45: RI | CT45: RI | CV45: RI | CX45: RI | CZ45: RI | DB45: RI | DD45: RI | DF45: RI | DH45: PICKUP | DJ45: TRIM | DL45: TRIM | DN45: TRIM
A46: 2037 | B46: University Townhomes | C46: Marpac | D46: 5 | F46: Bob | H46: 3025 NE 130th Street, Seattle WA | CZ46: GW | DB46: PT | DD46: PT | DF46: PT | DH46: RI | DJ46: RI | DL46: RI | DM46: TRIM | DN46: TRIM | DP46: TRIM
A47: 2049 | B47: Reserve Lynnwood Rebuild | C47: Exxel Pacific | D47: 296 | E47: Summer 17 | F47: Orlando / Bob | CL47: GW | CP47: GW | CR47: RI | CT47: RI | CV47: RI | CX47: RI | CZ47: RI | DB47: RI | DD47: RI | DF47: RI | DH47: RI | DJ47: TRIM | DL47: TRIM | DN47: TRIM | DP47: TRIM | DR47: TRIM
A48: 2045 | B48: GRE Notch | C48: GRE | D48: 158 | F48: Mitch / Bob | CQ48: GW | CR48: GW | CT48: GW | CV48: RI | CX48: RI | CZ48: RI | DB48: RI | DD48: RI | DF48: RI | DH48: RI | DJ48: RI | DL48: RI | DM48: TRIM | DN48: TRIM | DP48: TRIM | DR48: TRIM | DT48: TRIM | DV48: TRIM | DX48: TRIM
A49: 2057 | B49: Plaza | C49: Natural & Built | D49: 111 | F49: Reuben / Bob | CT49: GW | CV49: PT | CX49: PT | CZ49: PT | DB49: RI | DD49: RI | DF49: RI | DH49: RI | DJ49: RI | DL49: RI | DN49: RI | DP49: RI | DQ49: TRIM | DR49: TRIM | DT49: TRIM | DV49: TRIM | DX49: TRIM
A50: 2041 | B50: Luna 2749 California Ave | C50: Chinn | D50: 108 | E50: Summer 17 | F50: Rick / Joe | CO50: GW | CP50: GW | CR50: PT | CT50: PT | CV50: PT | CX50: PT | CZ50: RI | DB50: RI | DD50: RI | DF50: RI | DH50: RI | DJ50: RI | DL50: RI | DN50: RI | DP50: RI | DR50: TRIM | DT50: TRIM | DV50: TRIM | DX50: TRIM
A51: 2052 | B51: 5th & Roy | C51: Farrell | D51: 107 | F51: Thaddeus / Joe | CQ51: GW | CR51: GW | CT51: PT | CV51: PT | CX51: PT | CZ51: RI | DB51: RI | DD51: RI | DF51: RI | DH51: RI | DJ51: RI | DL51: RI | DN51: RI | DP51: RI | DQ51: TRIM | DR51: TRIM | DT51: TRIM | DV51: TRIM | DX51: TRIM | DZ51: TRIM
A52: 2053 | B52: Bellevue Parkside | C52: Compass | D52: 136 | E52: 43101 | F52: Victor / Bob | CR52: GW | CT52: GW | CV52: PT | CX52: PT | CZ52: PT | DB52: PT | DD52: PT | DE52: RI | DF52: RI | DH52: RI | DJ52: RI | DL52: RI | DN52: RI | DP52: RI | DR52: RI | DT52: TRIM | DV52: TRIM | DX52: TRIM | DZ52: TRIM | EB52: TRIM | ED52: TRIM | EF52: TRIM
A53: 2054 | B53: Blueprint 800 5th Ave | C53: Blueprint | D53: 68 | E53: 43177 | F53: Thaddeus / Joe | CY53: GW | CZ53: GW | DA53: PT | DB53: PT | DD53: PT | DF53: RI | DH53: RI | DJ53: RI | DL53: RI | DN53: RI | DP53: RI | DR53: RI | DT53: RI | DV53: RI | DX53: RI | DZ53: TRIM | EB53: TRIM | ED53: TRIM | EF53: TRIM
A54: 2051 | B54: Vail Apartments | C54: Compass | D54: 163 | E54: Winter 18 | F54: Bob | CY54: GW | CZ54: GW | DB54: PT | DD54: PT | DF54: PT | DH54: RI | DJ54: RI | DL54: RI | DN54: RI | DP54: RI | DR54: RI | DT54: RI | DV54: RI | DX54: RI | DZ54: TRIM | EB54: TRIM | ED54: TRIM | EF54: TRIM | EH54: COVID | EJ54: TRIM | EL54: TRIM
A55: 2058 | B55: Howell | C55: Blueprint | D55: 77 | F55: Reuben / Bob | DK55: GW | DL55: PT | DN55: PT | DP55: PT | DQ55: RI | DR55: RI | DT55: RI | DV55: RI | DX55: RI | DZ55: RI | EB55: RI | ED55: RI | EF55: TRIM | EH55: COVID | EJ55: TRIM | EL55: TRIM | EN55: TRIM | EP55: TRIM | ER55: TRIM | ET55: TRIM
A56: 2059 | B56: Meeker | C56: GRE | D56: 365 | F56: Rick, Anthony / Joe | DK56: GW | DL56: PT | DN56: RI | DP56: RI | DR56: RI | DT56: RI | DV56: RI | DX56: RI | DZ56: RI | EB56: RI | ED56: RI | EF56: RI | EH56: COVID | EJ56: RI | EL56: RI | EN56: RI | EP56: RI | ER56: RI | ET56: TRIM | EV56: TRIM | EX56: TRIM | EZ56: TRIM | FB56: TRIM | FD56: TRIM
A57: 2056 | B57: Acme Farms | C57: Exxel Pacific | D57: 321 | F57: Mitch, Thaddeus / Joe | DO57: GW | DP57: GW | DR57: PT | DT57: PT | DU57: RI | DV57: RI | DX57: RI | DZ57: RI | EB57: RI | ED57: RI | EF57: RI | EH57: COVID | EJ57: RI | EL57: RI | EN57: RI | EP57: RI | ER57: RI | ET57: TRIM | EV57: TRIM | EX57: TRIM | EZ57: TRIM | FB57: TRIM | FD57: TRIM | FF57: TRIM | FH57: TRIM | FJ57: TRIM
A58: 2063 | B58: Aria Flats | C58: Compass | D58: 102 | F58: Orlando / Bob | DY58: GW | DZ58: GW | EB58: GW | ED58: PT | EF58: PT | EH58: COVID | EJ58: RI | EL58: RI | EN58: RI | EP58: RI | ER58: RI | ET58: RI | EV58: RI | EX58: RI | EZ58: RI | FB58: TRIM | FD58: TRIM | FF58: TRIM | FH58: TRIM | FJ58: TRIM
A59: 2074 | B59: Buddha Jewel Monastery | C59: Marpac | D59: n/a | F59: Jordan | ER59: GW | ET59: RI | EV59: RI | EX59: RI | EZ59: RI | FB59: TRIM | FL59: GW | FN59: RI | FP59: RI | FR59: TRIM | FT59: TRIM | FV59: TRIM
A60: 2061 | B60: Columbia City | C60: Exxel Pacific | D60: 242 | F60: Victor | EB60: GW | ED60: GW | EF60: GW | EG60: PT | EH60: COVID | EJ60: PT | EL60: PT | EN60: RI | EP60: RI | ER60: RI | ET60: RI | EV60: RI | EX60: RI | EZ60: RI | FB60: RI | FD60: RI | FF60: RI | FH60: RI | FJ60: RI | FL60: TRIM | FN60: TRIM | FP60: TRIM | FR60: TRIM | FT60: TRIM | FV60: TRIM | FX60: TRIM | FZ60: TRIM
A61: 2064 | B61: Jabooda Melody | C61: Jabooda | D61: 186 | F61: Reuben | EB61: GW | ED61: GW | EF61: PT | EH61: COVID | EJ61: PT | EL61: RI | EN61: RI | EP61: RI | ER61: RI | ET61: RI | EV61: RI | EX61: RI | EZ61: RI | FB61: RI | FD61: RI | FF61: RI | FH61: RI | FJ61: RI | FL61: TRIM | FN61: TRIM | FP61: TRIM | FR61: TRIM | FT61: TRIM | FV61: TRIM | FX61: TRIM | FZ61: TRIM | GB61: TRIM
A62: 2066 | B62: Fireside Flats | C62: Compass | D62: 102 | F62: Orlando | FA62: GW | FB62: GW | FD62: GW | FF62: PT | FH62: RI | FJ62: RI | FL62: RI | FN62: RI | FP62: RI | FR62: TRIM | FT62: TRIM | FV62: TRIM | FX62: TRIM | FZ62: TRIM | GB62: TRIM
A63: 2055 | B63: Dockside | C63: Blueprint | D63: 98 | F63: Orlando | EX63: GW | EZ63: GW | FB63: PT | FD63: PT | FF63: PT | FH63: RI | FJ63: RI | FL63: RI | FN63: RI | FP63: RI | FR63: RI | FT63: TRIM | FV63: TRIM | FX63: TRIM | FZ63: TRIM | GB63: TRIM | GD63: TRIM
A64: 2060 | B64: Marina Square | C64: Compass | D64: 270 | F64: Anthony | DR64: GW | DT64: GW | DV64: GW | DW64: PT | DX64: PT | DZ64: PT | EB64: PT | ED64: PT | EF64: PT | EG64: RI | EH64: COVID | EJ64: HOLD | EL64: HOLD | EN64: HOLD | EP64: HOLD | ER64: HOLD | ET64: HOLD | EV64: HOLD | EX64: HOLD | EZ64: HOLD | FB64: RI | FD64: RI | FF64: RI | FH64: RI | FJ64: RI | FL64: RI | FN64: RI | FP64: RI | FR64: RI | FT64: RI | FV64: RI | FX64: TRIM | FZ64: TRIM | GB64: TRIM | GD64: TRIM | GF64: TRIM | GH64: TRIM | GJ64: TRIM
A65: 2076 | B65: Yesler Terrace Bldg B | C65: Compass | D65: 215 | F65: Mitch | EX65: GW | EZ65: GW | FB65: PT | FD65: PT | FF65: PT | FH65: RI | FJ65: RI | FL65: RI | FN65: RI | FP65: RI | FR65: RI | FT65: RI | FV65: RI | FX65: RI | FZ65: RI | GB65: RI | GC65: TRIM | GD65: TRIM | GF65: TRIM | GH65: TRIM | GJ65: TRIM
A66: 2075 | B66: Everett Rockefeller | C66: Braseth | D66: 165 | F66: Reuben | FC66: GW | FD66: GW | FF66: GW | FH66: PT | FJ66: PT | FL66: PT | FN66: RI | FP66: RI | FR66: RI | FT66: RI | FV66: RI | FX66: RI | FZ66: RI | GB66: RI | GD66: TRIM | GF66: TRIM | GH66: TRIM | GJ66: TRIM | GL66: TRIM
A67: 2069 | B67: Theory U-District | C67: Exxel Pacific | D67: 171 | F67: Rick | FD67: GW | FF67: GW | FH67: PT | FJ67: PT | FL67: PT | FN67: RI | FP67: RI | FR67: RI | FT67: RI | FV67: RI | FX67: RI | FZ67: RI | GB67: RI | GD67: TRIM | GF67: TRIM | GH67: TRIM | GJ67: TRIM | GL67: TRIM
A68: 2079 | B68: Crown Hill Mixed Use | C68: BMDC | D68: 54 | F68: Tommy | FF68: GW | FH68: PT | FJ68: RI | FL68: HOLD | FN68: RI | FP68: RI | FR68: RI | FT68: RI | FV68: RI | FX68: RI | FZ68: RI | GB68: RI | GC68: TRIM | GD68: TRIM | GF68: TRIM | GH68: TRIM | GJ68: TRIM | GL68: TRIM | GN68: TRIM | GP68: TRIM | GR68: TRIM | GT68: TRIM | GV68: TRIM
A69: 2067 | B69: Edmond 99 | C69: GRE | D69: 192 | F69: Jordan | FC69: GW | FD69: GW | FF69: GW | FH69: PT | FJ69: PT | FL69: PT | FN69: RI | FP69: RI | FR69: RI | FT69: RI | FV69: RI | FX69: RI | FZ69: RI | GB69: RI | GD69: RI | GF69: RI | GH69: TRIM | GJ69: TRIM | GL69: TRIM | GN69: TRIM
A70: 2081 | B70: 400 Queen Anne | C70: Compass | D70: 143 | F70: Thaddeus | FL70: GW | FN70: GW | FP70: PT | FR70: PT | FT70: RI | FV70: RI | FX70: RI | FZ70: RI | GB70: RI | GD70: RI | GF70: RI | GH70: RI | GJ70: TRIM | GL70: TRIM | GN70: TRIM | GP70: TRIM | GR70: TRIM | GT70: TRIM | GV70: TRIM | GX70: TRIM
A71: 2096 | B71: SunDowner | C71: Chinn | D71: 27 | F71: Thaddeus/Steven | GN71: RI | GP71: RI | GR71: RI | GT71: TRIM | GV71: TRIM | GX71: TRIM | GZ71: TRIM | HB71: TRIM
A72: 2078 | B72: 112 Lake Street | C72: Compass | D72: 141 | F72: Victor | FJ72: GW | FL72: GW | FN72: PT | FP72: PT | FR72: PT | FT72: RI | FV72: RI | FX72: RI | FZ72: RI | GB72: RI | GD72: RI | GF72: RI | GH72: RI | GJ72: RI | GL72: RI | GN72: RI | GP72: RI | GR72: TRIM | GT72: TRIM | GV72: TRIM | GX72: TRIM | GZ72: TRIM | HB72: TRIM | HD72: TRIM | HF72: TRIM
A73: 2071 | B73: 1405 Dexter | C73: Chinn | D73: 160 | F73: Reuben | FX73: ON HOLD | FZ73: ON HOLD | GB73: ON HOLD | GD73: GW | GF73: GW | GH73: PT | GJ73: PT | GL73: PT | GM73: RI | GN73: RI | GP73: RI | GR73: RI | GT73: RI | GV73: RI | GX73: RI | GZ73: RI | HB73: RI | HD73: TRIM | HF73: TRIM | HH73: TRIM | HJ73: TRIM
A74: 2085 | B74: Basalt | C74: Blueprint | D74: 77 | F74: Anthony | FX74: ON HOLD | FZ74: ON HOLD | GB74: ON HOLD | GD74: GW | GF74: GW | GH74: PT | GJ74: PT | GL74: PT | GM74: RI | GN74: RI | GP74: RI | GR74: RI | GT74: RI | GV74: RI | GX74: RI | GZ74: RI | HB74: RI | HD74: RI | HF74: TRIM | HH74: TRIM | HJ74: TRIM | HL74: TRIM | HN74: TRIM | HP74: TRIM
A75: 2080 | B75: Redmond Grand - Bldg B | C75: Compass | D75: 311 | F75: Orlando | FX75: ON HOLD | FZ75: ON HOLD | GB75: ON HOLD | GD75: GW | GF75: GW | GH75: PT | GJ75: PT | GL75: PT | GM75: RI | GN75: RI | GP75: RI | GR75: RI | GT75: RI | GV75: RI | GX75: RI | GZ75: RI | HB75: RI | HD75: RI | HF75: RI | HH75: TRIM | HJ75: TRIM | HL75: TRIM | HN75: TRIM | HP75: TRIM | HR75: TRIM | HT75: TRIM | HV75: TRIM
A76: 2088 | B76: Gridline (Knights of Columbus) | C76: SRM | D76: 178 | F76: Steven/Rick | GI76: GW | GJ76: GW | GL76: GW | GM76: PT | GN76: PT | GP76: RI | GR76: RI | GT76: RI | GV76: RI | GX76: RI | GZ76: RI | HB76: RI | HD76: RI | HF76: RI | HH76: RI | HJ76: TRIM | HL76: TRIM | HN76: TRIM | HP76: TRIM | HR76: TRIM | HT76: TRIM | HV76: TRIM
A77: 2086 | B77: LIZA | C77: Compass | D77: 207 | F77: Mitch | FX77: ON HOLD | FZ77: ON HOLD | GB77: ON HOLD | GD77: GW | GF77: GW | GH77: PT | GJ77: PT | GL77: PT | GM77: RI | GN77: RI | GP77: RI | GR77: RI | GT77: RI | GV77: RI | GX77: RI | GZ77: RI | HB77: RI | HD77: RI | HF77: RI | HH77: RI | HJ77: TRIM | HL77: TRIM | HN77: TRIM | HP77: TRIM | HR77: TRIM | HT77: TRIM | HV77: TRIM | HX77: TRIM
A78: 2082 | B78: Northgate | C78: GRE | D78: 235 | F78: Tommy | FL78: GW | FN78: GW | FP78: GW | FR78: PT | FT78: PT | FV78: RI | FX78: ON HOLD | FZ78: ON HOLD | GB78: ON HOLD | GD78: PT | GF78: RI | GH78: RI | GJ78: RI | GL78: RI | GN78: RI | GP78: RI | GR78: RI | GT78: RI | GV78: RI | GX78: RI | GZ78: RI | HB78: RI | HD78: RI | HF78: TRIM | HH78: TRIM | HJ78: TRIM | HL78: TRIM | HN78: TRIM | HP78: TRIM | HR78: TRIM | HT78: TRIM | HV78: TRIM | HX78: TRIM | HZ78: TRIM
A79: 2090 | B79: Chronicle | C79: Blueprint | D79: 78 | F79: Julio/Tommy | GT79: GW | GV79: GW | GX79: PT | GZ79: PT | HB79: RI | HD79: RI | HF79: RI | HH79: RI | HJ79: RI | HL79: RI | HN79: RI | HP79: RI | HR79: TRIM | HT79: TRIM | HV79: TRIM | HX79: TRIM | HZ79: TRIM | IB79: TRIM | ID79: TRIM | IF79: TRIM
A80: 2084 | B80: Willows | C80: GRE | D80: 195 | F80: Jordan | FX80: ON HOLD | FZ80: ON HOLD | GB80: ON HOLD | GE80: GW | GF80: GW | GH80: GW | GJ80: PT | GL80: PT | GN80: PT | GP80: PT | GR80: PT | GT80: RI | GV80: RI | GX80: RI | GZ80: RI | HB80: RI | HD80: RI | HF80: RI | HH80: RI | HJ80: RI | HL80: RI | HN80: RI | HP80: RI | HR80: TRIM | HT80: TRIM | HV80: TRIM | HX80: TRIM | HZ80: TRIM | IB80: TRIM | ID80: TRIM | IF80: TRIM
A81: 2077 | B81: Shoreline | C81: Intracorp | D81: 299 | F81: Thaddeus/Garret/Reuben | GP81: GW | GR81: GW | GV81: GW | GX81: GW | GZ81: GW | HB81: RI | HD81: RI | HF81: RI | HH81: RI | HJ81: RI | HL81: RI | HN81: RI | HP81: RI | HR81: RI | HT81: RI | HV81: RI | HX81: TRIM | HZ81: TRIM | IB81: TRIM | ID81: TRIM
A82: 2093 | B82: Symphony | C82: Jabooda | D82: 51 | F82: Anthony | GT82: GW | GV82: GW | GZ82: HOLD | HB82: HOLD | HD82: HOLD | HF82: HOLD | HH82: RI | HJ82: RI | HL82: RI | HN82: RI | HP82: RI | HR82: RI | HT82: RI | HV82: RI | HX82: RI | HZ82: TRIM | IB82: TRIM | ID82: TRIM | IF82: TRIM | IH82: TRIM | IJ82: TRIM | IL82: TRIM | IN82: TRIM
A83: 2094 | B83: Carrick | C83: Blueprint | D83: 86 | F83: Tommy | GX83: GW | GZ83: PT | HB83: PT | HD83: PT | HF83: HOLD | HH83: RI | HJ83: RI | HL83: RI | HN83: RI | HP83: RI | HR83: RI | HT83: RI | HV83: RI | HX83: RI | HZ83: TRIM | IB83: TRIM | ID83: TRIM | IF83: TRIM | IH83: TRIM | IJ83: TRIM | IL83: TRIM | IN83: TRIM
A84: 2087 | B84: Northgate (11201 Roosevelt) | C84: Exxel Pacific | D84: 295 | F84: Victor/Mitch | GT84: GW | GV84: GW | GX84: PT | GZ84: PT | HB84: PT | HD84: GW | HF84: RI | HH84: RI | HJ84: RI | HL84: RI | HN84: RI | HP84: RI | HR84: RI | HT84: RI | HV84: RI | HX84: RI | HZ84: RI | IB84: RI | ID84: TRIM | IF84: TRIM | IH84: TRIM | IJ84: TRIM | IL84: TRIM | IN84: TRIM
A85: 2089 | B85: 24th & Market | C85: Holland | D85: 238 | F85: Rick/Steven | HB85: GW | HD85: GW | HF85: PT | HH85: PT | HJ85: PT | HL85: PT | HM85: RI | HN85: RI | HP85: RI | HR85: RI | HT85: RI | HV85: RI | HX85: RI | HZ85: RI | IB85: RI | ID85: TRIM | IF85: TRIM | IH85: TRIM | IJ85: TRIM | IL85: TRIM | IN85: TRIM | IP85: TRIM | IR85: TRIM
A86: 2098 | B86: Trailside 2 | C86: Chinn | D86: 170 | F86: Orlando | HL86: GW | HN86: GW | HP86: PT | HR86: PT | HT86: PT | HU86: RI | HV86: RI | HX86: RI | HZ86: RI | IB86: RI | ID86: RI | IF86: RI | IH86: RI | IJ86: TRIM | IL86: TRIM | IN86: TRIM | IP86: TRIM | IR86: TRIM | IT86: TRIM | IV86: TRIM | IX86: TRIM | IZ86: TRIM | JB86: TRIM
A87: 2092 | B87: Reed Apartments | C87: Blueprint | D87: 125 | F87: Reuben | HI87: GW | HJ87: GW | HL87: GW | HN87: GW | HP87: PT | HR87: PT | HT87: PT | HU87: RI | HV87: PT | HX87: RI | HZ87: RI | IB87: RI | ID87: RI | IF87: RI | IH87: RI | IJ87: RI | IL87: RI | IN87: RI | IP87: RI | IR87: TRIM | IT87: TRIM | IV87: TRIM | IX87: TRIM | IZ87: TRIM | JB87: TRIM
A88: 2097 | B88: Marysville - Ph1 | C88: Intracorp | D88: 228 | F88: Garrett/Mitch | HW88: GW | HX88: GW | HZ88: GW | IB88: RI | ID88: RI | IF88: RI | IH88: RI | IJ88: RI | IL88: RI | IN88: RI | IP88: RI | IR88: RI | IT88: TRIM | IV88: TRIM | IX88: TRIM | IZ88: TRIM | JB88: TRIM
A89: 2101 | B89: Bella on Broadway Water Repipe | C89: F&M | D89: na | F89: Anthony/Joe | HZ89: RI | IB89: RI
A90: 2105 | B90: 3000 Western | C90: Compass | D90: 219 | F90: CANCELLED
A91: 2099 | B91: 300 W Republican | C91: Kirtley Cole | D91: 169 | F91: Jordan/Rick | IE91: GW | IF91: GW | IH91: PT | IJ91: PT | IL91: RI | IN91: RI | IP91: RI | IR91: RI | IT91: RI | IV91: RI | IX91: TRIM | IZ91: TRIM | JB91: TRIM | JD91: TRIM | JF91: TRIM | JH91: TRIM
A92: 2104 | B92: Big 1410 | C92: BMDC | D92: 24 | F92: Tommy/Ben | IF92: GW | IH92: GW | IJ92: PT | IL92: RI | IN92: RI | IP92: RI | IR92: RI | IT92: RI | IV92: RI | IX92: RI | IZ92: RI | JB92: RI | JD92: RI | JF92: TRIM | JH92: TRIM | JJ92: TRIM | JL92: TRIM | JN92: TRIM | JP92: TRIM | JR92: TRIM | JT92: TRIM | JV92: TRIM
A93: 2103 | B93: Northgate M2 | C93: Compass | D93: 234 | F93: Victor/Orlando | IE93: GW | IF93: GW | IH93: GW | IJ93: PT | IL93: PT | IN93: RI | IP93: RI | IR93: RI | IT93: RI | IV93: RI | IX93: RI | IZ93: RI | JB93: RI | JD93: RI | JF93: RI | JH93: RI | JJ93: TRIM | JL93: TRIM | JN93: TRIM | JP93: TRIM | JR93: TRIM | JT93: TRIM | JV93: TRIM | JX93: TRIM
A94: 2107 | B94: 68th & Roosevelt | C94: Chinn | D94: 244 | F94: Rick/Orlando | IV94: GW | IX94: PT | IZ94: PT | JB94: PT | JD94: RI | JF94: RI | JH94: RI | JJ94: RI | JL94: RI | JN94: RI | JP94: RI | JR94: RI | JT94: RI | JV94: RI | JX94: TRIM | JZ94: TRIM | KB94: TRIM | KD94: TRIM | KF94: TRIM | KH94: TRIM | KJ94: TRIM | KL94: TRIM | KN94: TRIM
A95: 2109 | B95: Marysville - Ph2 | C95: Intracorp | D95: 246 | F95: Garrett/Mitch | IZ95: GW | JB95: GW | JD95: RI | JF95: RI | JH95: RI | JJ95: RI | JL95: RI | JN95: RI | JP95: RI | JR95: RI | JT95: RI | JV95: RI | JX95: RI | JZ95: TRIM | KB95: TRIM | KD95: TRIM | KF95: TRIM | KH95: TRIM | KJ95: TRIM | KL95: TRIM
A96: 2112 | B96: BIG3 | C96: BMDC | D96: 20 | F96: Tommy | JD96: GW | JF96: GW | JH96: RI | JJ96: RI | JL96: RI | JN96: RI | JP96: RI | JR96: RI | JT96: RI | JV96: TRIM | JX96: TRIM | JZ96: TRIM | KB96: TRIM | KD96: TRIM | KF96: TRIM | KH96: TRIM
A97: 2111 | B97: Northgate M3 | C97: Compass | D97: 186 | F97: Victor | JJ97: GW | JL97: GW | JN97: PT | JP97: PT | JR97: RI | JT97: RI | JV97: RI | JX97: RI | JZ97: RI | KB97: RI | KD97: RI | KF97: RI | KH97: RI | KJ97: TRIM | KL97: TRIM | KN97: TRIM | KP97: TRIM | KR97: TRIM | KT97: TRIM | KV97: TRIM | KX97: TRIM | KZ97: TRIM | LB97: TRIM | LD97: TRIM
A98: 2116 | B98: The V Apartments | C98: SRM | D98: 166 | JX98: GW | JZ98: GW | KB98: PT | KD98: PT | KF98: RI | KH98: RI | KJ98: RI | KL98: RI | KN98: RI | KP98: RI | KR98: RI | KT98: RI | KV98: RI | KX98: RI | KZ98: RI | LB98: TRIM | LD98: TRIM | LF98: TRIM | LH98: TRIM | LJ98: TRIM | LL98: TRIM | LN98: TRIM | LP98: TRIM | LR98: TRIM
A99: 2114 | B99: Ballard Blossom | C99: Holland | D99: 239 | JZ99: GW | KB99: GW | KD99: PT | KF99: PT | KH99: RI | KJ99: RI | KL99: RI | KN99: RI | KP99: RI | KR99: RI | KT99: RI | KV99: RI | KX99: RI | KZ99: RI | LB99: RI | LD99: TRIM | LF99: TRIM | LH99: TRIM | LJ99: TRIM | LL99: TRIM | LN99: TRIM | LP99: TRIM | LR99: TRIM | LT99: TRIM
A100: 2110 | B100: Roosevelt Manor | C100: Sierra | D100: 137 | F100: Start Q2 2026 | JZ100: GW | KB100: GW | KD100: PT | KF100: PT | KH100: RI | KJ100: RI | KL100: RI | KN100: RI | KP100: RI | KR100: RI | KT100: RI | KV100: RI | KX100: RI | KZ100: RI | LB100: RI | LD100: TRIM | LF100: TRIM | LH100: TRIM | LJ100: TRIM | LL100: TRIM | LN100: TRIM | LP100: TRIM | LR100: TRIM | LT100: TRIM
...

Sheet Job Info
B1: =Schedule!B1 -> Job Name | C1: =Schedule!C1 -> GC | D1: Units | E1: Original Contract | G1: Contract w/ CO's | I1: Franklin Costs to date | J1: As-Bid Eng Budget | K1: Frank Cost/unit | L1: Insurance Type | M1: GC PM | N1: GC Sup | O1: GC PE | P1: Developer | Q1: Architect | R1: Structural | S1: Acoustical | T1: ADA Consultant | U1: Interior Design | V1: Engineer | W1: Levels Above | X1: Levels Below | Y1: Concrete | Z1: Wood
E2: Total | F2: Per unit | G2: Total | H2: Per Unit
A3: =Schedule!A2 -> 2001 | B3: =Schedule!B2 -> 230 Broadway | C3: =Schedule!C2 -> SRM | D3: 234 | E3: 2026045.6 | F3: =E3/D3 -> 8658.3147 | G3: 2121873.5 | H3: =G3/D3 -> 9067.8355 | I3: 21979 | J3: 30000 | K3: =I3/Schedule!D2 -> 93.92735 | Q3: Runberg
A4: =Schedule!A3 -> 2002 | B4: =Schedule!B3 -> Wedgewood | C4: =Schedule!C3 -> Exxel Pacific | D4: 91 | E4: 879530 | F4: =E4/D4 -> 9665.1648 | G4: 864597 | H4: =G4/D4 -> 9501.0659 | I4: 10520 | J4: 25000 | K4: =I4/Schedule!D3 -> 115.6044
A5: =Schedule!A4 -> 2003 | B5: =Schedule!B4 -> Evanston Space | C5: =Schedule!C4 -> Exxel Pacific | D5: 5 | F5: =E5/D5 -> 0 | H5: =G5/D5 -> 0 | I5: 8475 | K5: =I5/Schedule!D4 -> 302.67857
A6: =Schedule!A5 -> 2005 | B6: =Schedule!B5 -> Indigo/Kavela | C6: =Schedule!C5 -> Chinn | D6: 66 | E6: 501500 | F6: =E6/D6 -> 7598.4848 | G6: 499368 | H6: =G6/D6 -> 7566.1818 | I6: 13668 | J6: 18000 | K6: =I6/Schedule!D5 -> 207.09091 | Q6: Johnson Architecture and Planning | V6: Rushing
A7: =Schedule!A6 -> 2006 | B7: =Schedule!B6 -> Bella Lago | C7: =Schedule!C6 -> ICC | D7: 319 | F7: =E7/D7 -> 0 | H7: =G7/D7 -> 0 | I7: 30611 | K7: =I7/Schedule!D6 -> 95.959248
A8: =Schedule!A7 -> 2008 | B8: =Schedule!B7 -> 101 Taylor | C8: =Schedule!C7 -> SRM | D8: 258 | F8: =E8/D8 -> 0 | H8: =G8/D8 -> 0 | I8: 56506 | K8: =I8/Schedule!D7 -> 219.0155 | O8: A.J. Haviland | Q8: Runberg | V8: Rushing
A9: =Schedule!A8 -> 2009 | B9: =Schedule!B8 -> Greenwood | C9: =Schedule!C8 -> Chinn | D9: 56 | E9: 384900 | F9: =E9/D9 -> 6873.2143 | G9: 392855 | H9: =G9/D9 -> 7015.2679 | I9: 4895 | J9: 5000 | K9: =I9/Schedule!D8 -> 87.410714 | Q9: Studio Meng Strazzara
A10: =Schedule!A9 -> 2010 | B10: =Schedule!B9 -> Old Town | C10: =Schedule!C9 -> Chinn | D10: 149 | E10: 1469800 | F10: =E10/D10 -> 9864.4295 | G10: 1386419 | H10: =G10/D10 -> 9304.8255 | I10: 10463 | J10: 20000 | K10: =I10/Schedule!D9 -> 70.221477 | Q10: Weber Thompson | W10: 8
A11: =Schedule!A10 -> 2011 | B11: =Schedule!B10 -> Barrett Park | C11: =Schedule!C10 -> Chinn | D11: 117 | E11: 813050 | F11: =E11/D11 -> 6949.1453 | G11: 869823.5 | H11: =G11/D11 -> 7434.3889 | I11: 12487 | J11: 25000 | K11: =I11/Schedule!D10 -> 106.7265 | Q11: Studio Meng Strazzara | V11: Rushing
A12: =Schedule!A11 -> 2012 | B12: =Schedule!B11 -> 8th Ave | C12: =Schedule!C11 -> Exxel Pacific | D12: 162 | E12: 1394655 | F12: =E12/D12 -> 8608.9815 | G12: 1393316 | H12: =G12/D12 -> 8600.716 | I12: 15613 | K12: =I12/Schedule!D11 -> 96.376543 | Q12: NK | V12: Pressler
A13: =Schedule!A12 -> 2013 | B13: =Schedule!B12 -> NE 63rd | C13: =Schedule!C12 -> Exxel Pacific | D13: 112 | E13: 959780 | F13: =E13/D13 -> 8569.4643 | G13: 966156 | H13: =G13/D13 -> 8626.3929 | I13: 18532 | J13: 25000 | K13: =I13/Schedule!D12 -> 165.46429 | P13: Intra-Corp | Q13: Runberg | V13: Pressler | W13: 6 | X13: 1 | Y13: 2 | Z13: 5
A14: =Schedule!A14 -> 2018 | B14: =Schedule!B14 -> Astro | C14: =Schedule!C14 -> SRM | D14: 211 | E14: 2499585 | F14: =E14/D14 -> 11846.374 | G14: 2524038.5 | H14: =G14/D14 -> 11962.268 | I14: 24000 | K14: =I14/Schedule!D14 -> 113.74408 | M14: Eric Petersen | N14: John Schwab / James Wilkins | O14: Andrew Withnell | P14: SRM | Q14: Runberg | R14: DCI Engineers | S14: SSA Acoustics | V14: Pressler | W14: 6 | X14: 2 | Y14: 3 | Z14: 5
A15: =Schedule!A15 -> 2017 | B15: =Schedule!B15 -> 36 Stone | C15: =Schedule!C15 -> Exxel Pacific | D15: 119 | E15: 1373148 | F15: =E15/D15 -> 11539.059 | G15: 1365227 | H15: =G15/D15 -> 11472.496 | I15: 18000 | K15: =I15/Schedule!D15 -> 151.2605 | M15: Tyson Scheenstra / Tommy Booth | N15: Brad Carpenter | O15: Tommy Booth | P15: Mack Urban | Q15: Baylis | R15: CPL | S15: SSA Acoustics | T15: Karen Braitmayer | U15: ObjectSpace | V15: Rushing | W15: 4 | X15: 1 | Y15: 1 | Z15: 4
A16: =Schedule!A16 -> 2022 | B16: =Schedule!B16 -> Interlake | C16: =Schedule!C16 -> Exxel Pacific | D16: 18 | E16: 232454 | F16: =E16/D16 -> 12914.111 | G16: 242637 | H16: =G16/D16 -> 13479.833 | I16: 4757 | K16: =I16/Schedule!D16 -> 264.27778 | M16: Tommy Booth | N16: Brad Carpenter | O16: Garret Olsen | P16: Mack Urban | Q16: Nicholson Kovalchick | R16: Michael Nouwens | W16: 3 | X16: 0 | Y16: 0 | Z16: 3
A17: =Schedule!A17 -> 2015 | B17: =Schedule!B17 -> Rooster | C17: =Schedule!C17 -> Exxel Pacific | D17: 197 | E17: 1935285 | F17: =E17/D17 -> 9823.7817 | G17: 2045883 | H17: =G17/D17 -> 10385.193 | I17: 48000 | K17: =I17/Schedule!D17 -> 243.65482 | L17: Not Wrap | M17: John Hughes | N17: Nick Amaya | O17: Ben Prigmore / Mason Seto | P17: Lake Union Partners | Q17: Weinstein AU | R17: CPL | S17: SSA Acoustics | T17: Endelman & Associates | V17: Rushing | W17: 7 | X17: 2 | Y17: 4 | Z17: 5
A18: =Schedule!A18 -> 2014 | B18: =Schedule!B18 -> Pike Motorworks | C18: =Schedule!C18 -> Exxel Pacific | D18: 241 | E18: 2661895 | F18: =E18/D18 -> 11045.207 | H18: =G18/D18 -> 0 | I18: 65000 | J18: 70000 | K18: =I18/Schedule!D18 -> 251.93798 | L18: Wrap | M18: Dave Biasini / Josh Purefoy | N18: Jeff Christiansen / Bill Armstrong | O18: Brett Johnston / Ben McCarty | P18: The Wolff Company | Q18: Weber Thompson | R18: CPL | T18: theACCESSpartnership | U18: Weber Thompson / Graham Baba | V18: Ecotope | W18: 7 | X18: 3 | Y18: 5 | Z18: 5
A19: =Schedule!A19 -> 2020 | B19: =Schedule!B19 -> Bellevue Main | C19: =Schedule!C19 -> SRM | D19: 256 | E19: 3415305 | F19: =E19/D19 -> 13341.035 | H19: =G19/D19 -> 0 | I19: NA | K19: NA | L19: Not Wrap | M19: Todd Rankin / Erik Benzel | N19: Bill Robinson / Jared Osborn | O19: Renay Luzama | P19: Pillar Properties / SRM | Q19: Benson & Bohl | R19: DCI Engineers | S19: SSA Acoustics | V19: Pressler | W19: 5 | X19: 2 | Y19: 3 | Z19: 4
A20: =Schedule!A20 -> 2019 | B20: =Schedule!B20 -> 8th Republic | C20: =Schedule!C20 -> Exxel Pacific | D20: 211 | E20: 2721210 | F20: =E20/D20 -> 12896.73 | H20: =G20/D20 -> 0 | I20: 70000 | K20: =I20/Schedule!D20 -> 331.75355 | L20: Wrap | M20: Dave Biasini / Brian Christensen | N20: Dan Phillips / Todd Tradal | O20: Joel Palmer / Sam Bernoski | P20: The Wolff Company | Q20: Runberg - Interior Miller Hull - Exterior | R20: CPL | S20: SSA Acoustics | T20: theACCESSpartnership | U20: Lair Design | V20: Rushing | W20: 8 | X20: 2 | Y20: 10 | Z20: 0
A21: =Schedule!A21 -> 2024 | B21: =Schedule!B21 -> Merrill Gardens | C21: =Schedule!C21 -> SRM | D21: 104 | E21: 1763480 | F21: =E21/D21 -> 16956.538 | H21: =G21/D21 -> 0 | I21: NA | K21: =I21/Schedule!D21 -> #VALUE! | L21: Not Wrap | M21: Bill Robinson | N21: James Wilkins | O21: Ben Robles | P21: Merrill Gardens / Pillar Properties | Q21: Urbal Architecture | R21: DCI Engineers | S21: SSA Acoustics | U21: NAC Architecture | V21: Abossein | W21: 7 | X21: 1 | Y21: 3 | Z21: 5
A22: =Schedule!A22 -> 2021 | B22: =Schedule!B22 -> Admiral | C22: =Schedule!C22 -> Exxel Pacific | D22: 136 | E22: 1558650 | F22: =E22/D22 -> 11460.662 | H22: =G22/D22 -> 0 | I22: 53260 | K22: =I22/Schedule!D22 -> 391.61765 | L22: Wrap | M22: Victor Vo / Justin Ripkin | N22: Scott Weston / Nic Christoffer | O22: Justin Ripkin | P22: Intra-Corp | Q22: Nicholson Kovalchick | R22: Panos (Yu & Troch..) | S22: SSA Acoustics | T22: Karen Braitmayer | U22: ObjectSpace | V22: Pressler | W22: 5 | X22: 1 | Y22: 2 | Z22: 4
A23: =Schedule!A23 -> 2023 | B23: =Schedule!B23 -> Hadley | C23: =Schedule!C23 -> Chinn | D23: 209 | E23: 2469500 | F23: =E23/D23 -> 11815.789 | H23: =G23/D23 -> 0 | I23: 28144 | K23: =I23/Schedule!D23 -> 134.66029 | L23: Not Wrap | M23: Charlie Poggemann | N23: Mark Pesanti / Sim Mooers | O23: Lauren Bjorndahl | P23: Legacy Partners | Q23: VIA Architecture | R23: Panos (Yu & Troch..) | S23: JGL Acoustics | T23: Karen Braitmayer | U23: Robin Chell Design | V23: Rushing | W23: 6 | X23: 1 | Y23: 3 | Z23: 4
A24: =Schedule!A24 -> 2028 | B24: =Schedule!B24 -> Reserve @ Lynnwood | C24: =Schedule!C24 -> Exxel Pacific | D24: 296 | E24: 2979880 | F24: =E24/D24 -> 10067.162 | H24: =G24/D24 -> 0 | I24: 20233 | K24: =I24/Schedule!D24 -> 68.35473 | L24: Not Wrap | M24: TJ Mellema / Coby Jones | N24: Brad Holz | P24: AVS Communities | Q24: Charles Morgan & Associates, LLC | V24: N/A | W24: 5 | X24: 1 | Y24: 1 | Z24: 5
A25: =Schedule!A28 -> 2027 | B25: =Schedule!B28 -> 550 Broadway | C25: =Schedule!C28 -> Exxel Pacific | D25: 170 | E25: 2230810 | F25: =E25/D25 -> 13122.412 | G25: 2275444 | H25: =G25/D25 -> 13384.965 | I25: 39854 | K25: =I25/Schedule!D28 -> 234.43529 | L25: Wrap | M25: Justin Gotcher / Chris Austin | N25: Brian Proctor | O25: Chris Austin | P25: Intra-Corp | Q25: Nicholson Kovalchick | V25: Pressler
A26: =Schedule!A26 -> 2026 | B26: Boren (Fox & Finch) | C26: =Schedule!C26 -> Synnergy | D26: 49 | E26: 825370 | F26: =E26/D26 -> 16844.286 | H26: =G26/D26 -> 0 | I26: 17344 | K26: =I26/Schedule!D26 -> 353.95918 | L26: Not Wrap | M26: Matt Stewart / Ron Auld / Jamie Creek | N26: Aaron Steinke | O26: Michele Lee
A27: =Schedule!A25 -> 2025 | B27: =Schedule!B25 -> The Cora | C27: =Schedule!C25 -> Exxel Pacific | D27: 75 | E27: 1179300 | F27: =E27/D27 -> 15724 | G27: 1202633 | H27: =G27/D27 -> 16035.107 | I27: 27970 | K27: =I27/Schedule!D25 -> 372.93333 | L27: Not Wrap | M27: Victor Vo / Ben Prigmore | N27: Tim Conner | O27: Jola Bielecki | P27: Barrientos, LLC
A28: =Schedule!A27 -> 2029 | B28: =Schedule!B27 -> Parsonage | C28: =Schedule!C27 -> Exxel Pacific | D28: 83 | E28: 1113220 | F28: =E28/D28 -> 13412.289 | G28: 1129452 | H28: =G28/D28 -> 13607.855 | I28: 20121 | K28: =I28/Schedule!D27 -> 242.42169 | L28: Not Wrap | M28: Victor Vo / Ben Prigmore | N28: Bill Armstrong | O28: Mason Seto
A29: =Schedule!A36 -> 2030 | B29: =Schedule!B36 -> East Union | C29: =Schedule!C36 -> Exxel Pacific | D29: 144 | E29: 2135080 | F29: =E29/D29 -> 14826.944 | G29: 2322781 | H29: =G29/D29 -> 16130.424 | K29: =I29/Schedule!D29 -> 0 | L29: Not Wrap | M29: Coby Jones | N29: Steve Booth | O29: Matt Anderson | P29: Lake Union Partners
A30: 2031 | B30: Issaquah Gateway (Anthology) | C30: Exxel Pacific | D30: 398 | E30: 5051600 | F30: =E30/D30 -> 12692.462 | G30: 5187754 | H30: =G30/D30 -> 13034.558 | L30: Not Wrap | M30: Ben McCarty/Tim Spink | N30: Dennis Schlosser | O30: Connor Jungkuntz | P30: Wolff | Q30: Weinstein AU
A31: 2032 | B31: Luna | C31: Blueprint | D31: 71 | E31: 685300 | F31: =E31/D31 -> 9652.1127 | G31: 726903 | H31: =G31/D31 -> 10238.07 | L31: Not Wrap | M31: Andrew Withnell | N31: Scott McSpadden
A32: 2033 | B32: Vuecrest (LUX) | C32: Compass | D32: 137 | E32: 2447600 | F32: =E32/D32 -> 17865.693 | G32: 2286188 | H32: =G32/D32 -> 16687.504 | K32: =I32/Schedule!D42 -> 0 | L32: Wrap | M32: Ryan Ames/Vince Dennison | N32: Todd Mortenson | O32: Dan Peck | P32: Continental
A33: 2034 | B33: Park Lane (VODA) | C33: Compass | D33: 128 | E33: 1784000 | F33: =E33/D33 -> 13937.5 | G33: 1842651 | H33: =G33/D33 -> 14395.711 | K33: =I33/Schedule!D35 -> 0 | L33: Wrap | M33: Frank Weaver | N33: Mike Horgan | O33: Kait O'Neill | P33: Continental | Q33: Johnson Braund | R33: Yu & Trochalakis | U33: Sechrist Design
A34: 2035 | B34: 162 Ten | C34: Natural & Built | D34: 97 | E34: 717400 | F34: =E34/D34 -> 7395.8763 | G34: =E34+5500 -> 722900 | H34: =G34/D34 -> 7452.5773 | K34: =I34/Schedule!D30 -> 0 | L34: Not Wrap | M34: Tyson Cornett
A35: 2036 | B35: Westridge | C35: Exxel Pacific | D35: 31 | E35: 388515 | F35: =E35/D35 -> 12532.742 | G35: 418677 | H35: =G35/D35 -> 13505.71 | K35: =I35/Schedule!D36 -> 0 | L35: Not Wrap | M35: David Strid | N35: Shon Geer | O35: Jose Tapia
A36: 2037 | B36: University Apartments (MYSA) | C36: Marpac | D36: 122 | E36: 1920850 | F36: =E36/D36 -> 15744.672 | G36: 2076783 | H36: =G36/D36 -> 17022.811 | K36: =I36/Schedule!D32 -> 0 | L36: Not Wrap | M36: Evan Chan | N36: Doyle Gustafson
A37: 2038 | B37: 2nd & John | C37: Compass | D37: 80 | E37: 1175378 | F37: =E37/D37 -> 14692.225 | G37: 1195660 | H37: =G37/D37 -> 14945.75 | L37: Wrap | M37: Justin Anderson | N37: Kurt Weagant | O37: Karl Clocksin | P37: Continental
A38: 2039 | B38: Ravello Gas Piping | C38: Shelter Holdings | D38: na | E38: 54900 | L38: Not Wrap | M38: Renay Luzama | N38: Bill Robinson
A39: 2040 | B39: Brooklyn 65 | C39: Blueprint | D39: 55 | E39: 604000 | F39: =E39/D39 -> 10981.818 | G39: 624171 | H39: =G39/D39 -> 11348.564 | L39: Not Wrap | M39: Andrew Withnell | N39: Mike Sanderson | O39: Kyle Stenson
A40: 2041 | B40: Luna | C40: Chinn | D40: 108 | E40: 1766205 | F40: =E40/D40 -> 16353.75 | G40: 1878824 | H40: =G40/D40 -> 17396.519 | L40: Not Wrap | M40: Joe Hanley | N40: James Casal | O40: Amir Molavi
A41: 2042 | B41: Metro Line Flats | C41: Shelter Holdings | D41: 72 | E41: 906587 | F41: =E41/D41 -> 12591.486 | G41: =E41+15775 -> 922362 | H41: =G41/D41 -> 12810.583 | L41: Not Wrap | M41: Renay Luzama | N41: Bill Robinson | O41: Shonna Hiatt | P41: Shelter Holdings
A42: 2043 | B42: Aegis Mercer Island | C42: Compass | D42: 98 | E42: 1576200 | F42: =E42/D42 -> 16083.673 | G42: 1583445 | H42: =G42/D42 -> 16157.602 | L42: Not Wrap | M42: Howard Jacobsen | N42: Ryan O'Connell | O42: Alina Lutenco | P42: Aegis
A43: 2044 | B43: Track 66 | C43: Blueprint | D43: 75 | E43: 832900 | F43: =E43/D43 -> 11105.333 | G43: 855264 | H43: =G43/D43 -> 11403.52 | L43: Not Wrap | M43: Andrew Withnell | N43: Scott McSpadden / Stefan Fjeldsted | O43: Kyle Stenson | P43: Blueprint
A44: 2045 | B44: Notch Apartments | C44: GRE | D44: 158 | E44: 1898200 | F44: =E44/D44 -> 12013.924 | G44: 2110205 | H44: =G44/D44 -> 13355.728 | L44: Not Wrap | M44: Gavin Erickson / Christian Knorr / Jin Lee | N44: Jason Hill | O44: Michelle Deng
A45: 2046 | B45: 4218 Roosevelt (Sundodger) | C45: Marpac | D45: 110 | E45: 1648500 | F45: =E45/D45 -> 14986.364 | G45: 1721867 | H45: =G45/D45 -> 15653.336 | L45: Not Wrap | M45: Pat Nakamura | N45: Todd Weeks | O45: Joey Mar
A46: 2047 | B46: Greenlake (Crew) | C46: GRE | D46: 70 | E46: 475800 | F46: =E46/D46 -> 6797.1429 | G46: 553189 | H46: =G46/D46 -> 7902.7 | L46: Not Wrap | M46: Victor Vo | N46: John Bolle | O46: Astra Persue / Titus Uomoto
A47: 2048 | B47: Ballinger (The 205) | C47: GRE | D47: 72 | E47: 498700 | F47: =E47/D47 -> 6926.3889 | G47: 517068 | H47: =G47/D47 -> 7181.5 | L47: Not Wrap | M47: Victor Vo | N47: Dan Schaeffer | O47: Astra Persue / Titus Uomoto
A48: 2049 | B48: Lynnwood Reserve Rebuild | C48: Exxel Pacific | D48: 296 | E48: 2588665 | F48: =E48/D48 -> 8745.4899 | G48: =E48+100761 -> 2689426 | H48: =G48/D48 -> 9085.8986 | L48: Not Wrap | M48: Coby Jones | N48: Martin Solorio | O48: ? | P48: Reserve
A49: 2050 | B49: 2100 Madison (Avant) | C49: Compass | D49: 50 | E49: 897800 | F49: =E49/D49 -> 17956 | G49: 918566 | H49: =G49/D49 -> 18371.32 | L49: Not Wrap | M49: Scott Miller | N49: Pat McCabe | O49: Steve Garka
A50: 2051 | B50: Vail Apartments | C50: Compass | D50: 163 | E50: 2672000 | F50: =E50/D50 -> 16392.638 | L50: Not Wrap | M50: Justin Anderson | N50: Will Fenton | O50: Jeff Seeb | P50: AAA Management
A51: 2052 | B51: 5th & Roy | C51: F&M | D51: 107 | E51: 2134000 | F51: =E51/D51 -> 19943.925 | L51: Not Wrap | M51: Sean McKenna | N51: Scott Weston | O51: Michael McKenna | P51: Farrel McKenna
A52: 2053 | B52: Bellevue Parkside | C52: Compass | D52: 135 | E52: 2241309 | F52: =E52/D52 -> 16602.289 | L52: Wrap | M52: Dan Peck | N52: Todd Mortenson | O52: Jacob Jeske | P52: Continental
A53: 2054 | B53: 800 5th | C53: Blueprint | D53: 63 | E53: 785600 | F53: =E53/D53 -> 12469.841 | L53: Not Wrap | M53: Andrew Withnell | N53: Bill Shore | O53: Stefan Fjeldsted | P53: Blueprint
A54: 2055 | B54: Dockside | C54: Blueprint | D54: 98 | E54: =1142340+151002 -> 1293342 | F54: =E54/D54 -> 13197.367 | L54: Not Wrap
A55: 2056 | B55: Acme Farms | C55: Exxel Pacific | D55: 321 | E55: 5877400 | F55: =E55/D55 -> 18309.657 | L55: Wrap | M55: Josh Purefoy / Steven Hall | N55: Kyle Harmia | O55: Kenji Norwood | P55: Intra-Corp
A56: 2057 | B56: Kirkland Plaza | C56: Natural & Built | D56: 111 | E56: 1098897 | F56: =E56/D56 -> 9899.973 | L56: Not Wrap | M56: Tyson Cornett | N56: Don Cunningham | O56: na | P56: Natural & Built
A57: 2058 | B57: Howell | C57: Blueprint | D57: 76 | E57: 928800 | F57: =E57/D57 -> 12221.053 | L57: Not Wrap | M57: Andrew Withnell | N57: Scott McSpadden / Stefan Fjeldsted | O57: Kyle Stenson | P57: Blueprint
A58: 2059 | B58: Meeker | C58: GRE | D58: 365 | E58: 4378750 | F58: =E58/D58 -> 11996.575 | L58: Not Wrap | M58: Victor Vo | N58: Kirk Swenson / Dan Schaeffer / Brad Carpenter / Scott Messer | O58: Titus Uomoto | P58: GRE
A59: 2060 | B59: Marina Square | C59: Compass | D59: 270 | E59: 5307510 | F59: =E59/D59 -> 19657.444 | L59: Not Wrap | M59: Rich Swedstedt / Ryan Ames | N59: Bill Christopherson / Richard Moore | O59: Derya O'Rourke / Alina Lutenco | P59: Sound West Group | Q59: Encore
A60: 2061 | B60: Columbia City | C60: Exxel Pacific | D60: 242 | E60: 4305550 | F60: =E60/D60 -> 17791.529 | L60: Wrap | M60: Brian Christensen / Zachary Vandiver | N60: Tim Conner | O60: Armando Espinosa
A61: 2062 | B61: Origin 206 | C61: Marpac | D61: Cancelled | L61: Not Wrap
A62: 2063 | B62: Aria Flats | C62: Compass | D62: 102 | E62: 1535729 | F62: =E62/D62 -> 15056.167 | L62: Wrap | M62: Daniel Marks / Matt Johnson | N62: Scott Donder | O62: Qasim Gill
A63: 2064 | B63: Jabooda Melody | C63: Jabooda | D63: 186 | E63: 2952000 | F63: =E63/D63 -> 15870.968 | L63: Not Wrap | M63: Kaitlyn Huynh | N63: Patrick Fischer
A64: 2065 | B64: Flag Lot | C64: Holland | D64: Cancelled
A65: 2066 | B65: Fireside Flats | C65: Compass | D65: 102 | E65: 1565600 | F65: =E65/D65 -> 15349.02 | M65: Jeff Seeb | N65: Taylor Turay | O65: Kait O'neal
A66: 2067 | B66: Edmonds 99 | C66: GRE | D66: 192 | E66: 2485780 | F66: =E66/D66 -> 12946.771 | M66: Rob Kralis | N66: Paul Mandish | O66: Ben Lek
A67: 2068 | B67: Alloy | C67: Schuchart | D67: Cancelled
A68: 2069 | B68: Theory U-District | C68: Exxel Pacific | D68: 171 | E68: 3872036 | F68: =E68/D68 -> 22643.485 | M68: Brian Christensen/Matt Sims | N68: Bill Armstrong | O68: Bill Levison
A69: 2070 | B69: Beacon Crossing | C69: Chinn | D69: Cancelled | F69: =E69/D69 -> #VALUE!
A70: 2071 | B70: 1405 Dexter | C70: Chinn | D70: 160 | E70: 2966700 | F70: =E70/D70 -> 18541.875 | M70: Danny Fletcher | N70: Joe Vasey | O70: Mike McClure
A71: 2072 | B71: 56th Ballard | C71: Exxel Pacific | D71: Cancelled
A72: 2073 | B72: 57th Ballard | C72: Exxel Pacific | D72: Cancelled
A73: 2074 | B73: Buddha Jewel Monastery | C73: Marpac | D73: NA | E73: 333600 | M73: Michelle Ip | N73: Jeff Fogarty | O73: Joey Mar / Maggie Cheng
A74: 2075 | B74: Everett Rockefeller | C74: Braseth | D74: 165 | E74: 2387900 | F74: =E74/D74 -> 14472.121 | M74: Tyler Mitchell / Mark Braseth Jr. | N74: Kawika Takasaki | O74: Ken Tews / Kevin Mullen
A75: 2076 | B75: Yesler Terrace Phase 2 | C75: Compass | D75: 215 | E75: 3112600 | F75: =E75/D75 -> 14477.209 | M75: Scott Miller / Justin Anderson / Brian Welsh | N75: Will Fenton / Brandon Houghton | O75: Chris Waters
A76: 2077 | B76: Shoreline 147th | C76: Intracorp | D76: 299 | E76: 5560950 | F76: =E76/D76 -> 18598.495 | M76: Tod Werner / | N76: Jim Arnett / Lars Swenson / Chris Jones | O76: Thomas Detrick / Kyle Skow
A77: 2078 | B77: 112 Lake Street | C77: Compass | D77: 141 | E77: 2711810 | F77: =E77/D77 -> 19232.695 | M77: Dan Peck / Howard Jacobsen | N77: Todd Mortensen / Kenis Loven | O77: Bridget Elliott / Kay Stertz
A78: 2079 | B78: Crown Hill | C78: BMDC | D78: 54 | E78: 992600 | F78: =E78/D78 -> 18381.481 | M78: Wayd Munro / Tim Kairez | N78: Ricky Pulley | O78: Grace Peterson
A79: 2080 | B79: Redmond Grand | C79: Compass | D79: 311 | E79: 5848945 | F79: =E79/D79 -> 18806.897 | M79: Nick Cunningham | N79: Chris Auld / Nate Happenstall / David Ottolino | O79: Derek Uchiumi / Logan Brooks / Oleg Chebotarev / Brittany Duhs
A80: 2081 | B80: 400 Queen Anne | C80: Compass | D80: 143 | E80: 2409160 | F80: =E80/D80 -> 16847.273 | M80: Dan Peck / Frank Weaver | N80: Csaba Orban | O80: Daniel Burdick
A81: 2082 | B81: Northgate Phase 2 | C81: GRE | D81: 235 | E81: 3417420 | F81: =E81/D81 -> 14542.213 | M81: Ken James / Gavin Erickson | N81: Jeff Gerde / Jason Hill | O81: Caitlin Supe
A82: 2083 | B82: Bellevue Plaza | C82: Compass | D82: 312 | F82: =E82/D82 -> 0
A83: 2084 | B83: Willows | C83: GRE | D83: 195 | E83: 3398000 | F83: =E83/D83 -> 17425.641 | M83: Jin Lee | N83: Richard Erickson | O83: Jesse Dehnert
A84: 2085 | B84: Basalt | C84: Blueprint | D84: 77 | E84: 1288000 | F84: =E84/D84 -> 16727.273
A85: 2086 | B85: LIZA | C85: Compass | D85: 207 | E85: 5369136 | F85: =E85/D85 -> 25937.855 | M85: Gary Moss | N85: Gino Cecsarini | O85: Jordan Dye
A86: 2087 | B86: Northgate (11201 Roosevelt) | C86: Exxel Pacific | D86: 295 | E86: =5456100+110000 -> 5566100 | F86: =E86/D86 -> 18868.136 | M86: Steven Hall | N86: Nic Christoffer | O86: Reed Servizi / Brett Johnston
A87: 2088 | B87: Gridline | C87: SRM | D87: 178 | E87: =4086535+7250 -> 4093785 | F87: =E87/D87 -> 22998.792 | M87: Bill Robinson / Danielle Locklar | N87: James Wilkins | O87: Christian Dobbins / Jyoti Bhadrashetti
A88: 2089 | B88: 24th & Market | C88: Holland | D88: 238 | E88: 6052169 | F88: =E88/D88 -> 25429.282 | M88: Drew Shemchuck / David Vo / Elizabeth Roberts | N88: Seth Andersson / Charles "Casey" Dean | O88: Tony Sippl / Ashley Roman
A89: 2090 | B89: Chronicle | C89: Blueprint | D89: 78 | E89: 1455000 | F89: =E89/D89 -> 18653.846
A90: 2091 | B90: GRE U-District Remodel | C90: GRE | D90: NA | E90: 51144
A91: 2092 | B91: Reed Apartments | C91: Blueprint | D91: 125 | E91: 2456100 | F91: =E91/D91 -> 19648.8
A92: 2093 | B92: 4221 37th Ave S | C92: Jabooda | D92: 51 | E92: 1051120 | F92: =E92/D92 -> 20610.196 | M92: Kaitlyn Huynh | N92: Patrick Fischer
A93: 2094 | B93: Carrick | C93: Blueprint | D93: 86 | E93: 1689000 | F93: =E93/D93 -> 19639.535
A94: 2095 | B94: Josephine South | C94: StoryBuilt | D94: Cancelled
A95: 2096 | B95: SunDowner | C95: Chinn | D95: 27 | E95: 448000 | F95: =E95/D95 -> 16592.593 | N95: Tim Brennan
A96: 2097 | B96: Marysville | C96: Intracorp | D96: 228 | E96: 5135097 | F96: =E96/D96 -> 22522.355
A97: 2098 | B97: Trailside 2 | C97: Chinn | D97: 170 | E97: 6885880 | F97: =E97/D97 -> 40505.176 | M97: Joe Hanley | N97: Noel Baca | O97: Bonnie Laremore Brennan / Mike McClure
A98: 2099 | B98: KOZ on 3rd Ave West | C98: Kirtley Cole | D98: 169 | E98: 2950000 | F98: =E98/D98 -> 17455.621 | M98: Edgar Delgado / Corey Toepfer | N98: Nick Mosteller
A99: 2100 | B99: The Fir | C99: Braseth | D99: 204 | F99: =E99/D99 -> 0
A100: 2101 | B100: Bella on Broadway Repipe | C100: F&M | D100: NA | E100: 167100
...

Sheet Projects Bid
A1: Job # | B1: Job Name | C1: OWP Bid Date | D1: GC | E1: Units | F1: Base Bid | G1: Price/unit | H1: Owner | I1: Architect | J1: Engineer | K1: Area | L1: Start Date | M1: General Schedule | N1: Competitor | O1: Competitor Bid? | P1: Competitor | Q1: Competitor Bid? | R1: Competitor | S1: Competitor Bid? | T1: Notes
A2: BID | B2: Block 11 | C2: 42391 | D2: Exxel Pacific | E2: 386 | F2: 6599000 | G2: =F2/E2 -> 17095.855 | H2: Vulcan | I2: Runberg | J2: Ecotope | K2: South Lake Union | L2: 42613 | M2: 22 Months | N2: Wolfe Plumbing | P2: Ocean Park | R2: PSF Mechanical
A3: BID | B3: 44th Ave SW Apartments | C3: 42396 | D3: Blueprint | E3: 58 | F3: 569000 | G3: =F3/E3 -> 9810.3448 | H3: Blueprint | I3: Cone | J3: N/A | K3: West Seattle | L3: Spring 2016 | M3: ~16 Months | N3: DK Plumbing? | O3: Think it was $412,000 | T3: Mike Burdo sent Exh B on the following project that was put out to bid. On it there was the $412,000, which we think was for this project.
A4: BID | B4: East Union | C4: 42391 | D4: Exxel Pacific | E4: 144 | F4: 2063000 | G4: =F4/E4 -> 14326.389 | H4: Lake Union Partners | I4: Weinstein A+U | J4: Rushing | K4: Madrona | L4: Summer 2016 | M4: 18 Months | N4: Wolfe Plumbing | O4: Approx $2,013,000 | P4: Atlas Plumbing | Q4: Don't know
A5: BID | B5: Boylston Flats | C5: 42419 | D5: W.G. Clark | E5: 107 | F5: 1025000 | G5: =F5/E5 -> 9579.4393 | H5: Johnson-Carr | I5: S+H Works | J5: N/A | K5: Capitol Hill | L5: 42491 | M5: 15 Months
A6: BID | B6: Issaquah Gateway (SEE 2ND BID) | C6: 42426 | D6: Exxel Pacific | E6: 398 | F6: 4919200 | G6: =F6/E6 -> 12359.799 | H6: Wolff Company | I6: VIA | J6: Glumac | K6: Issaquah | L6: Summer 2016 | M6: 27 Months
A7: BID | B7: 66th & Roosevelt | C7: 42444 | D7: Exxel Pacific | E7: 206 | F7: 2996000 | G7: =F7/E7 -> 14543.689 | H7: HB Management | I7: Weinstein A+U | K7: Roosevelt
A8: BID | B8: 6505 15th Ave NE | C8: 42444 | D8: Exxel Pacific | E8: 222 | F8: 3343000 | G8: =F8/E8 -> 15058.559 | H8: Roosevelt Development Group | I8: GGLO | J8: PAE | K8: Roosevelt
A9: BID | B9: 103rd Avenue Apartments | C9: 42465 | D9: Chinn | E9: 162 | F9: 2867000 | G9: =F9/E9 -> 17697.531 | H9: Shintex Global Holdings, LLC | I9: GGLO | J9: Rushing | K9: Downtown Bellevue | N9: SJS Mechanical | O9: 2650000 | P9: Transit | Q9: Even less than SJS, but Chinn went with SJS
A10: BID | B10: Ravelo Apartments | C10: 42486 | D10: Shelter Holdings | E10: 102 | F10: 1465800 | G10: =F10/E10 -> 14370.588 | H10: Shelter Holdings | I10: SMR Architects | J10: Sider+Byers | K10: Redmond | L10: 42552 | M10: ~16 Months | N10: Sunrise Plumbing? | P10: Peltram | Q10: ~$160k lower
A11: BID | B11: Lake City Apartments | C11: 42496 | D11: Marpac | E11: 122 | F11: 1793000 | G11: =F11/E11 -> 14696.721 | I11: Studio19 Architects | J11: N/A | K11: Lake City | L11: 42705
A12: BID | B12: Vuecrest Apartments | C12: 42507 | D12: Compass | E12: 139 | F12: 2419000 | G12: =F12/E12 -> 17402.878 | H12: Continental Properties | I12: Encore Architects | J12: Emerald City | K12: Downtown Bellevue | L12: 42567 | M12: ~23 Months | N12: Aloisio Plumbing | O12: Don't know yet, but we are low so far. Update 5/17/16, Dan Peck told me Alosio was 5% low.
A13: BID | B13: 6921 Roosevelt Way NE | C13: 42508 | D13: Blueprint | E13: 71 | F13: 662800 | G13: =F13/E13 -> 9335.2113 | H13: Blueprint | I13: Cone | J13: N/A | K13: Roosevelt | L13: 42675 | N13: Tri-State | O13: Mike said the bids were so close they were almost matching
A14: BID | B14: Capitol Hill Lofts | C14: 42514 | D14: Marpac | E14: 55 | F14: 891000 | G14: =F14/E14 -> 16200 | H14: Vestus | I14: NK Architects | J14: N/A | K14: Capitol Hill | L14: Late 2016/early 17 | N14: Wolfe Plumbing originally bid it but pulled their number, so no competition | R14: Transit | S14: Within $60k | T14: Put bid in, he said we got it, then called back two weeks later and said that Transit got it. Classic case of us giving them a number and then they turn it over to Transit.
A15: BID | B15: Issaquah Gateway 2nd Time | C15: 42523 | D15: Exxel Pacific | E15: 398 | F15: 5049100 | G15: =F15/E15 -> 12686.181 | H15: Wolff Company | I15: VIA | J15: Glumac | K15: Issaquah | L15: Summer 2016 | M15: 27 Months | N15: Wolfe & Bigfoot possibly bid the mid-rise buildings, but sounds like no bidders on walk ups
A16: BID | B16: Park Lane Apartments | C16: 42534 | D16: Compass | E16: 128 | F16: 1839000 | G16: =F16/E16 -> 14367.188 | H16: Continental Properties | I16: Johnson Braund | J16: Emerald City | K16: Kirkland | L16: 42583 | M16: 21 Months | N16: SJS Mechanical | O16: "Very close" | P16: JD Plumbing
A17: BID | B17: Issaquah Senior Housing | C17: 42534 | D17: Exxel Pacific | E17: 146 | F17: 2249000 | G17: =F17/E17 -> 15404.11 | H17: Wolff Company | I17: VIA | J17: N/A | K17: Issaquah | L17: ? | M17: ? | N17: Bulldog | O17: 2055000 | T17: Bid to Halvorson, EP and Chinn
A18: BID | B18: 2nd & John | C18: 42565 | D18: Compass | E18: 80 | F18: 1179000 | G18: =F18/E18 -> 14737.5 | H18: Continental Properties | I18: Baylis | J18: Emerald City | K18: Capitol Hill | L18: 42614 | M18: ~16 Months
A19: BID | B19: 162 Ten | C19: 42576 | D19: Natural&Built | E19: 96 | F19: 698400 | G19: =F19/E19 -> 7275 | H19: Natural & Built | I19: Milbrandt Architects | J19: Pressler | K19: Redmond
A20: BID | B20: Cannery | C20: 42607 | D20: Exxel Pacific | E20: 54 | F20: 916400 | G20: =F20/E20 -> 16970.37 | H20: Barrientos | I20: Hewitt | J20: Rushing Narrative | K20: Pioneer Square | L20: Summer 2017
A21: BID | B21: Jefferson Park Apartments | C21: 42662 | D21: Marpac | E21: 49 | F21: 822000 | G21: =F21/E21 -> 16775.51 | I21: Encore Architects | K21: International District | L21: Not Sure | M21: Not sure | N21: Bulldog (got it) | O21: 700000 | P21: Tri-State (pulled) | Q21: 586000 | R21: Transit | S21: 930000
A22: BID | B22: Aegis Mercer Island | C22: 42682 | D22: Compass | E22: 89 | F22: 1481800 | G22: =F22/E22 -> 16649.438 | H22: Aegis | I22: Ankrom Moisan | J22: Coffman | K22: Mercer Island
A23: BID | B23: NE 65th Street | C23: 42690 | D23: Blueprint | E23: 55 | F23: 604000 | G23: =F23/E23 -> 10981.818 | H23: Blueprint | I23: Cone | J23: N/A | K23: Roosevelt | L23: Summer 2017
A24: BID | B24: NE 66th Street | C24: 42690 | D24: Blueprint | E24: 78 | F24: 839500 | G24: =F24/E24 -> 10762.821 | H24: Blueprint | I24: Cone | J24: N/A | K24: Roosevelt | L24: Summer 2017 | T24: Per conversation with Andrew on 11/30, he is probably giving us this job, but the 65th will probably go to the same plumber that did the west seattle job
A25: BID | B25: Issaquah Senior Housing | C25: 42704 | D25: Exxel Pacific | E25: 146 | F25: 2369000 | G25: =F25/E25 -> 16226.027 | H25: Wolff Company | I25: VIA | J25: Glumac | K25: Issaquah | L25: 42705 | M25: ? | N25: Aloisio Plumbing | O25: 2150000 | P25: Transit | Q25: 2350000 | R25: Wolff ended up getting this one | T25: Glumac had drawings this time
A26: BID | B26: 403 Dexter | C26: 42717 | D26: Synnergy | E26: 98 | F26: 1542000 | G26: =F26/E26 -> 15734.694 | H26: Wilshire | I26: VIA | J26: Glumac | K26: South Lake Union | L26: ? | M26: ?
A27: BID | B27: Issaquah Apartments | C27: 42726 | D27: Exxel Pacific | E27: 110 | F27: 1809400 | G27: =F27/E27 -> 16449.091 | H27: American Classic Homes | I27: Group Architect | J27: Ecotope | K27: Issaquah | L27: ?? | M27: ?? | N27: Edmonds Plumbing | O27: 1388500 | P27: United Plumbing | Q27: Not sure. Was told that Owner wants to work with United, and they have a relationship. They were cheaper too.
A28: BID | B28: Greenwood Apartments | C28: 42754 | D28: Rush Commerical | E28: 85 | F28: 1817800 | G28: =F28/E28 -> 21385.882 | H28: Greenwood Ave Investors | I28: Encore Architects | J28: Rushing | K28: Greenwood | L28: March, 2017 | M28: 14 months | N28: Dave Anderson provided a list of plumbing bidders, it was very long and very commercial
A29: BID | B29: Maple Leaf Flats Greenlake | C29: 42769 | D29: Charter | E29: 42 | F29: 724400 | G29: =F29/E29 -> 17247.619 | H29: Flatiron Properties | I29: Johnston Architects | J29: Sider+Byers | K29: Greenlake | L29: July, 2017 | M29: 13 months
A30: FYI | B30: Harbor Avenue | C30: NA | D30: Chinn | E30: 15 | F30: NA | G30: NA | K30: West Seattle | N30: SJS Mechanical | O30: 921000 | T30: Charlie asked us to look at it but hadn't realized that it was already committed to SJS. Would have been a good job.
A31: BID | B31: 4218 Roosevelt | C31: 42824 | D31: Chinn | E31: 110 | F31: 1485200 | G31: =F31/E31 -> 13501.818 | H31: G&K Brothers, Inc. | I31: Studio19 | J31: Coffman? | K31: University District | L31: ??? | M31: ???
A32: BID | B32: Bear Creek Apartments | C32: 42832 | D32: Fairfield | E32: 360 | F32: 5430700 | G32: =F32/E32 -> 15085.278 | H32: Fairfield Residential | I32: ARK Architects | J32: Interface Engineering | K32: Redmond | L32: Summer 17 | M32: Long time | N32: SJS Mechanical | P32: LOST TO JET INDUSTRIES BY 5 OR 6% | T32: I thought that Ocean Park and Allied Plumbing had submitted bids, but according to Justin with Fiarfield, they did not.
A33: BID | B33: 4218 Roosevelt | C33: 42863 | D33: Marpac | E33: 110 | F33: 1648500 | G33: =F33/E33 -> 14986.364 | H33: G&K Brothers, Inc. | I33: Studio19 | J33: Coffman? | K33: University District | L33: Late August 17 | M33: ??? | N33: SJS Mechanical | T33: Originally bid to Chinn. Owner re-bid it to Marpac. Chinn told us we were 20% low, so we raised our number to Marpac.
A34: BID | B34: Aegis Overlake | C34: 42873 | D34: Compass | E34: 118 | F34: 3210500 | G34: =F34/E34 -> 27207.627 | H34: Aegis | I34: Ankrom Moisan | J34: Coffman | K34: Bellevue | N34: Compass turned this project down. Exxel Pacific picked it up. Wolff got it for around $23k to $24k per unit.
A35: BID | B35: Metro Flats | C35: 42885 | D35: Shelter Holdings | E35: 72 | F35: 934800 | G35: =F35/E35 -> 12983.333 | H35: Shelter Holdings | I35: Johnston Architects | J35: N/A | K35: First Hill | L35: ? | M35: ?
A36: BID | B36: Auburn Town Center Apartments | C36: 42892 | D36: Compass | E36: 205 | F36: 3209000 | G36: =F36/E36 -> 15653.659 | H36: Merrill Gardens | I36: Urbal Architecture | J36: N/A | K36: Auburn | L36: ? | M36: ? | T36: BUDGET PRICING ONLY
A37: BID | B37: Bellevue Parkside | C37: 42908 | D37: Compass | E37: 136 | F37: 2592500 | G37: =F37/E37 -> 19062.5 | H37: Continental Properties | I37: Encore Architects | J37: Emerald City | K37: Bellevue | L37: Q1 2018 | M37: ? | N37: Tri-State | P37: SJS
A38: BID | B38: Bellevue Parkside Rebid | C38: 43126 | D38: Compass | E38: 136 | F38: =2623500-321000 -> 2302500 | G38: =F38/E38 -> 16930.147 | H38: Continental Properties | I38: Encore Architects | J38: Emerald City | K38: Bellevue | L38: Q1 2018 | M38: ? | N38: Tri-State | P38: SJS
A39: BID | B39: Columbia City Apartments | C39: 42912 | D39: Exxel Pacific | E39: 242 | F39: 3974000 | G39: =F39/E39 -> 16421.488 | H39: Lake Union Partners | I39: Weinstein A+U | J39: Rushing | K39: Columbia City | L39: ? | M39: ?
A40: NO BID | B40: 23rd & Jackson | C40: na | D40: Exxel Pacific | E40: 532 | H40: Vulcan | J40: Ecotope | N40: Hawk Mechanical got it, per Steve Sharrat
A41: BID | B41: 225 Roy | C41: 42979 | D41: Exxel Pacific | E41: 269 | F41: 5379300 | G41: =F41/E41 -> 19997.398 | H41: Barrientos | I41: GGLO | J41: Rushing | K41: Queen Anne | L41: Q2 2018 | M41: 23 months | N41: Wolff got it. | P41: Trademark Plbg | R41: JH Kelly | T41: Wolff got it for about $800,000 less than our price.
A42: BID | B42: 98th Ave Apartments | C42: 42993 | D42: Compass | E42: 79 | F42: 1342000 | G42: =F42/E42 -> 16987.342 | H42: Harbour Homes | I42: Group Architect | J42: Emerald City | K42: Bothell | L42: 43132 | M42: ? | N42: SJS Mechanical
A43: BID | B43: 98th Ave Apartments Rebid | C43: 43146 | D43: Compass | E43: 79 | F43: 1477000 | G43: =F43/E43 -> 18696.203 | H43: Harbour Homes | I43: Group Architect | J43: Emerald City | K43: Bothell | L43: 43191 | M43: ? | N43: SJS Mechanical? | T43: Compass did not get this project, it went to High Country
A44: BID | B44: South Bayview | C44: 42999 | D44: Compass | E44: 67 | F44: 1189500 | G44: =F44/E44 -> 17753.731 | H44: Pacific Housing NW | I44: Weinstein A+U | J44: Ecotope | K44: Beacon Hill | L44: ? | M44: ? | T44: As of 1/26/19, owner is still having permitting issues. Per conversation with Reid Bullock in October 2019, we were not low. Low bidder was at $15k/unit.
A45: BID | B45: Yoshikawa Mixed Use | C45: 43024 | D45: Marpac | E45: 24 | F45: 758900 | G45: =F45/E45 -> 31620.833 | H45: Yoshikawa Family | I45: Roger H. Newell | J45: N/A | K45: Magnolia | L45: ? | M45: ? | N45: Per Steve Sharratt, Kimco plumbing bid this back in July
A46: BID | B46: Interbay Apartments | C46: 43042 | D46: Graham | E46: 93 | F46: 1552600 | G46: =F46/E46 -> 16694.624 | H46: Pastakia Associates | I46: Urbal Architecture | J46: N/A | K46: Interbay | L46: 43191 | M46: ? | T46: Rushing was on this, got kicked off
A47: BID | B47: Avalon North Creek | C47: 43056 | D47: Avalon | E47: 316 | F47: 4710000 | G47: =F47/E47 -> 14905.063 | H47: Avalon Residential | I47: Rutledge Maul Architects | J47: N/A | K47: Mill Creek | L47: 43101 | M47: Long time | N47: Andgar? | T47: Per email from John Jaeger 1/18/18, we were within 5% of the top 3 plumbers. We did not get it.
A48: BUDGET | B48: Vail Apartments | C48: 43061 | D48: Compass | E48: 163 | F48: 2738000 | G48: =F48/E48 -> 16797.546 | H48: Zion Realty USA | I48: JRA Architects | J48: DC Engineering? | K48: Shoreline | L48: ? | M48: ?
A49: BUDGET | B49: 2100 E. Madison | C49: 43067 | D49: Compass | E49: 50 | F49: 897800 | G49: =F49/E49 -> 17956 | H49: JCMV LLC | I49: Weinstein A+U | J49: N/A | K49: Capitol Hill | L49: ? | M49: ?
A50: BID | B50: 800 5th Ave | C50: 43068 | D50: Blueprint | E50: 68 | F50: 785600 | G50: =F50/E50 -> 11552.941 | H50: Blueprint | I50: S+H Works | J50: N/A | K50: Queen Anne | L50: ? | M50: ?
A51: BID | B51: Totem Lake Apartments | D51: Lennar | F51: Decided not to bid | H51: Lennar | N51: Peltram
A52: BID | B52: Legacy West Seattle | C52: 43111 | D52: Compass | E52: 308 | F52: 5469500 | G52: =F52/E52 -> 17758.117 | H52: Legacy Partners | I52: Encore Architects | J52: Rushing | K52: West Seattle | L52: ? | M52: ?
A53: BID | B53: The Village | C53: 43130 | D53: Compass | E53: 104 | F53: 1598800 | G53: =F53/E53 -> 15373.077 | H53: Redmond Village Holdings | I53: Veer Architecture | J53: Abossein | K53: Redmond | N53: Atlas plumbing, per Steve Sharratt | P53: Per conversation with Allan on 4/12/18, Tri-state got it, was $200k lower
A54: BID | B54: ACME Farms | C54: 43131 | D54: Exxel & Venture | E54: 321 | F54: 5759300 | G54: =F54/E54 -> 17941.745 | H54: Intracorp | I54: Tiscarano Associates | J54: N/A | K54: International District | L54: End of 2018 | N54: Possibly SJS. Steve said the job was quoted on 8/25/17 to Keller and Consolidated.
A55: BID | B55: U-Place | C55: 43137 | D55: Marpac | E55: 243 | F55: 4045200 | G55: =F55/E55 -> 16646.914 | H55: University Place WA | I55: DLR Group | J55: DLR Group | K55: U-Village | L55: Spring 2018 | M55: ?
A56: BID | B56: Merrill Gardens Renton | C56: 43158 | D56: SRM | E56: 52 | F56: 997500 | G56: =F56/E56 -> 19182.692 | H56: Merrill Gardens | I56: Urbal Architecture | J56: na | K56: Renton | L56: ?
A57: BID | B57: Plaza Kirkland | C57: 43161 | D57: Natural&Built | E57: 107 | F57: 1128800 | G57: =F57/E57 -> 10549.533 | H57: Natural & Built | I57: Designs Northwest Architects | J57: Pressler | K57: Kirkland | L57: ?
A58: BID | B58: Triton Court Apartments | G58: =F58/E58 -> #DIV/0! | T58: Dad talked to Reid on 6/29/18, Compass is still proposing to the Owner. He made it sound like they wouldn't know until labor day. The excavation isn't right either, so there's more work that needs to be done there.
A59: BID | B59: Marina Square | C59: 43280 | D59: Compass | E59: 266 | F59: 5278000 | G59: =F59/E59 -> 19842.105 | N59: Herdman Plumbing | T59: Brent told dad he was $400k or $500k high to Herdman Plumbing
A60: BID | B60: North State Street Apartments | C60: 43301 | D60: Exxel Pacific | E60: 161 | F60: 3572000 | G60: =F60/E60 -> 22186.335 | N60: Andgar | P60: Lost to Wolff
A61: BUDGET | B61: Auburn Town Center Apartments | C61: 43307 | D61: Compass | E61: 226 | F61: 4746000 | G61: =F61/E61 -> 21000 | H61: Teutsch / Pillar | I61: Urbal Architecture | J61: N/A | K61: Auburn | L61: ? | M61: ? | N61: I GAVE A BUDGET OF $20K TO $21K PER UNIT | T61: I was told by Nick Cunningham with Compass that they gave a verbal committmet to Tri-State for this job. I got a follow up email from Nick on 12/18/18 that said Tri-State was over $2,000,000 lower than us. So that would be somewhere around $10,000/unit.
A62: BID | B62: Shoreline Apartments | C62: 43318 | D62: Exxel Pacific | E62: 122 | F62: 2186000 | G62: =F62/E62 -> 17918.033 | H62: Evergreen Point Redmond | I62: Caron | J62: Sider Byers | K62: Shoreline
A63: BUDGET | B63: 12th & Yesler | C63: 43319 | D63: Compass | E63: 296 | F63: 6216000 | G63: =F63/E63 -> 21000 | H63: Centric Partners, LLC | I63: Nicholson Kovalchick | J63: N/A | K63: Yesler | L63: ? | M63: ? | N63: I GAVE A BUDGET OF $20K TO $21K PER UNIT | T63: Owner did not go through with purchase of this property.
A64: BUDGET | B64: Canyon Park Apartments | C64: 43349 | D64: Compass | E64: 461 | F64: 8528500 | G64: =F64/E64 -> 18500 | H64: ? | K64: Canyon Park | T64: Compass is still waiting to hear from the Owner as of 1/26/19
A65: BUDGET | B65: Othello Square Condos | C65: 43350 | D65: Marpac | E65: 68 | F65: 1632000 | G65: =F65/E65 -> 24000 | T65: Heat pump water heaters, very different system. Owner decided in May 2019 to switch the project to prevailing wage, so we backed out of it. Got a call from DM Kelly estimator asking questions about it.
A66: BID | B66: Alloy Apartments | C66: 43742 | D66: PSW | E66: =73+82 -> 155 | F66: =1558800+1447400 -> 3006200 | G66: =F66/E66 -> 19394.839 | H66: PSW | I66: Johnston Architects | J66: Sider Byers | K66: Central District
A67: BUDGET | B67: BIG-1 Bell-Red Road | C67: 43413 | D67: Compass | E67: 160 | F67: 3120000 | G67: =F67/E67 -> 19500 | H67: BIG 1 LLC | I67: Encore Architects | J67: na | K67: Bellevue | N67: I GAVE A BUDGET OF $18.5K TO $19.5K PER UNIT | R67: Tri-State per Steve Sharrat | T67: Per email from Ryan Ames on 5/9/19: "For Big 1, LLC we ended up awarding to Tristate, they provided a budget that was 35% lower than your number and their credit for ABS in lieu of Cast was 30% more. Tristate has successfully completed many projects for us, and the Sr. PM was confident that their number was complete. "
A68: BID | B68: 1200 NE 50th St Apartments | C68: 43419 | D68: Fairbank Construction | E68: 49 | F68: 887000 | G68: =F68/E68 -> 18102.041 | H68: BonaFide Ventures | I68: Weinstein A+U | J68: na | K68: University District
A69: BUDGET | B69: Yesler Terrace | C69: 43434 | D69: Compass | E69: 548 | F69: =E69*G69 -> 10686000 | G69: 19500 | H69: Seattle Tench, LLC | I69: Ankrom Moisan | J69: None Listed | K69: Yesler | N69: I GAVE A BUDGET OF $19.5K TO $20.5K PER UNIT | T69: Lost it, not sure who to.
A70: BUDGET | B70: CRUX 19022 Aurora | D70: Compass | I70: Clark Barnes | T70: This project went to someone else, not Compass
A71: BID | B71: Spuds Greenlake | C71: 43462 | D71: Blueprint | E71: 61 | F71: 795900 | G71: =F71/E71 -> 13047.541 | H71: Blueprint | I71: Cone Architecture | J71: na | K71: Greenlake
A72: BID | B72: Rhythm Apartments | C72: 43467 | D72: Chinn | E72: 127 | F72: 1943400 | G72: =F72/E72 -> 15302.362 | H72: Yuans H & H Properties | I72: d/Arch LLC | J72: Emerald City | K72: University District | T72: Venture sent an invitation to bid on this project on 8/30/19.
A73: BID | B73: Pike & Pine Manor | C73: 43476 | D73: Chinn | E73: 53 | F73: 746500 | G73: =F73/E73 -> 14084.906 | H73: Xue Wei Investments | I73: Caron | J73: Sider Byers | K73: Capitol Hill | L73: Summer 2019 | T73: The Owner decided not to proceed with this project.
A74: BID | B74: 417 2nd Ave Apartments | C74: 43486 | D74: Schuchart | E74: 95 | F74: 2078400 | G74: =F74/E74 -> 21877.895 | H74: Hycroft Investment Inc | I74: Johnston Architects | J74: Sider Byers
A75: BID | B75: Alderwood South Apartments | C75: 43489 | D75: Compass | E75: 240 | F75: 3042000 | G75: =F75/E75 -> 12675 | H75: Wolff | I75: Katerra | J75: Katerra | K75: Lynnwood | N75: Tri-State | T75: Compass told me that they were high to Synergy Construction and
A76: BID | B76: Crown Hill | C76: 43496 | D76: Braseth | E76: 54 | F76: 1135400 | G76: =F76/E76 -> 21025.926 | H76: Braseth | I76: Johnston Architects | J76: Sider Byers | K76: Crown Hill | T76: On hold.
A77: BID | B77: Paradise Lake | C77: 43517 | D77: Compass | E77: 360 | F77: 4760000 | G77: =F77/E77 -> 13222.222 | H77: Wolff | I77: Katerra | J77: Katerra | K77: Maltby | T77: Per conversation with Reid Bullock in October 2019, we were low on this job. The only other bid was $3.5mil higher.
A78: BID | B78: Columbia City Condos | C78: 43518 | D78: Schuchart | E78: 155 | F78: 3040800 | G78: =F78/E78 -> 19618.065 | H78: Storybuilt (PSW) | I78: Johnston Architects | J78: na | K78: Columbia City
A79: BID | B79: Rivertrail Apartments | C79: 43522 | D79: Mill Creek | E79: 233 | F79: 3727200 | G79: =F79/E79 -> 15996.567 | H79: Mill Creek | I79: GGLO | J79: N/A | K79: Redmond | T79: Mill Creek said they had several bidders, and that I was in the middle of the pack. The bids varied by several hundred 100k's.
A80: BID | B80: Legends of Everett | C80: 43551 | D80: Exxel Pacific | E80: 320 | F80: 4122000 | G80: =F80/E80 -> 12881.25 | H80: Dominium | I80: BCRA | J80: ? | K80: Everett | L80: ? | N80: Wolff got it. | O80: 4107000 | P80: Trademark Plbg | Q80: =O80-400000 -> 3707000 | T80: Craig tell me Wolff’s base bid was $4,107,000. OWP base bid was $4,122,000. Craig claims there was no other reason other than the low number for Wolff to get the project. Breaks down to high by $46.88 per unit. Trademark Plumbing was over $400,000 low on the project and after some questions from Craig, they withdrew their bid.
A81: BID | B81: Redmond Flats | C81: 43556 | D81: Compass | E81: 102 | F81: 1821000 | G81: =F81/E81 -> 17852.941 | H81: Tejal Pastakia | I81: Encore Architects | J81: Glumac | K81: Redmond | N81: JD got it, probably 100k beneath us | P81: Atlas walked away | R81: Priority, Compass wouldn't use | T81: Compass gave us a second look at this but we still lost it.
A82: BID | B82: 206 Place Condos | C82: 43572 | D82: Marpac | E82: 65 | F82: 1293000 | G82: =F82/E82 -> 19892.308 | H82: Doug Mar | I82: Hewitt | J82: Tres West BOD | K82: Pioneer Square | N82: We were high to Bulldog Plumbing, but Will Ng walked us into the number
A83: BID | B83: Scout Apartments | C83: 43573 | D83: Compass | E83: 59 | F83: 1474000 | G83: =F83/E83 -> 24983.051 | H83: Kim Faust, George John | I83: Dahlin Group | J83: HV Engineering | K83: Kirkland | T83: Owner decided not to proceed with this project.
A84: BID | B84: Redmond Flats - 2nd Bid | C84: 43609 | D84: Compass | E84: 102 | F84: 1753000 | G84: =F84/E84 -> 17186.275 | H84: Tejal Pastakia | I84: Encore Architects | J84: Glumac | K84: Redmond | N84: JD got it, probably 100k beneath us | P84: Atlas walked away | R84: Priority, Compass wouldn't use | T84: Compass gave us a second look at this but we still lost it.
A85: BID | B85: 206 Place Condos - 2ND BID | C85: 43620 | D85: Marpac | E85: 65 | F85: 1185300 | G85: =F85/E85 -> 18235.385 | H85: Doug Mar | I85: Hewitt | J85: Tres West BOD | K85: Pioneer Square | L85: 43770
A86: BID | B86: 8105 Greenwood | C86: 43633 | D86: Blueprint | E86: 66 | F86: 863500 | G86: =F86/E86 -> 13083.333 | H86: Blueprint | T86: Project is being sold to another developer.
A87: BUDGET | B87: Overlake Place Parcel A (Seritage Place) | C87: 43661 | D87: Compass | E87: 442 | F87: 7381400 | G87: =F87/E87 -> 16700 | H87: Mack Urban | I87: GGLO | J87: Rusing | K87: Redmond (Old Sears lot) | T87: Per Dan Peck email 9/9/19, "Just got word that the developer went another direction"
A88: BUDGET | B88: Edmonds Senior Living | C88: 43678 | D88: Compass | E88: 126 | F88: 2470800 | G88: =F88/E88 -> 19609.524 | H88: CA Ventures | I88: Ankrom Moisan | J88: DC Engineers | K88: Edmonds
A89: BID | B89: Edmonds 99 | C89: 43707 | D89: GRE | E89: 192 | F89: 2371900 | G89: =F89/E89 -> 12353.646 | H89: GRE | I89: Studio Meng Strazzara | J89: na | K89: Edmonds
A90: BUDGET | B90: 12th & Yesler | C90: 43728 | D90: W.G. Clark | E90: 269 | F90: =4599000+95000 -> 4694000 | G90: =F90/E90 -> 17449.814 | H90: Centric Partners | I90: Clark Barnes | J90: na | K90: Yesler | T90: Per email from Jason on 9/20/19, we were 16% high to one other bidder. Found out on 9/24/19 from Geoff Wood of Proctor Sales that Wolff was the other bidder.
A91: BID | B91: Mira Apartments | C91: 43734 | D91: Farrell McKenna | E91: 112 | F91: 1130700 | G91: =F91/E91 -> 10095.536 | H91: Redpoint Development Group | I91: Ross Deckman & Associates | J91: N/A | K91: Burien | T91: Not proceeding because of federal funding.
A92: BID | B92: 1200 NE 50th St Apartments | C92: 43747 | D92: Marpac | E92: 49 | F92: 874800 | G92: =F92/E92 -> 17853.061 | H92: Bonafide Ventures | I92: Weinstein A+U | J92: na | K92: University District
A93: BID | B93: Mira Apartments - 2nd Bid | C93: 43769 | D93: Farrell McKenna | E93: 112 | F93: 1151400 | G93: =F93/E93 -> 10280.357 | H93: Redpoint Development Group | I93: Ross Deckman & Associates | J93: N/A | K93: Burien | T93: Not proceeding because of federal funding.
A94: BUDGET | B94: 112 Lake Street | C94: 43767 | D94: Compass | E94: 142 | F94: 2734000 | G94: =F94/E94 -> 19253.521 | H94: Continental Properties | I94: Encore | J94: na | K94: Kirkland
A95: BID | B95: Reserve at Arlington | C95: 43768 | D95: Exxel Pacific | E95: 150 | F95: 1466000 | G95: =F95/E95 -> 9773.3333 | H95: Reserve | I95: Tiscarano Associates | J95: Windsor | K95: Arlington | N95: West Coast | O95: 1115000 | P95: Andgar | Q95: 1115000 | R95: Wolff | S95: 1420000 | T95: Coby gave us all the numbers from this bid, see to the left. West Coast plumbing has 18 L&I violations.
A96: BUDGET | B96: Hilltop | C96: 43774 | D96: Chinn | E96: 68 | F96: 1199500 | G96: =F96/E96 -> 17639.706 | H96: Hunters Capital | I96: Studio Meng Strazzara | J96: na | K96: Capitol Hill | T96: Charlie says we came in second, but the bottom bidder was missing something. There were a total of 4 bids. The one higher than us was only half a percent above us.
A97: BUDGET | B97: Brooklyn Ave | C97: 44148 | D97: Chinn | E97: 186 | F97: 5529000 | G97: =F97/E97 -> 29725.806 | H97: Fields Holdings | I97: Jackson Main | J97: na | K97: University District
A98: BID | B98: 2517 Eastlake | C98: 43789 | D98: Exxel Pacific | E98: 183 | F98: 3596000 | G98: =F98/E98 -> 19650.273 | H98: Washington Holdings | I98: Hewitt | J98: Rushing | K98: Eastlake
A99: BID | B99: Fireside Flats | C99: 43789 | D99: Compass | E99: 102 | F99: 1734000 | G99: =F99/E99 -> 17000 | H99: Tejal Pastakia | I99: Encore | J99: na | K99: Roosevelt
A100: BUDGET | B100: Auburn Divine Court | C100: 43791 | D100: Chinn | E100: 98 | F100: 1599000 | G100: =F100/E100 -> 16316.327 | H100: MSRE Apartment | I100: Benny Kim | J100: Robison Engineering | K100: Auburn
...

Sheet BbQuantityLink
A1: <?xml version="1.0" encoding="utf-8"?>_x000D_ <QuantityLinks Version="3">_x000D_ <Links />_x000D_ <Filesets />_x000D_ <Guids />_x000D_ </QuantityLinks> | B1: 1

Sheet Projects NOT Bid
A1: Job Name | B1: Invite Date | C1: GC | D1: Units | E1: Owner | F1: Area | G1: Reason Did Not Bid | H1: Competitor | I1: Competitor Bid? | J1: Notes
A2: Bothell Commons Phase II | B2: 44876 | C2: Avalon Bay | D2: 400 | E2: Avalon Bay | F2: Bothell | G2: Too busy to get around to
A3: Market Square | B3: 44831 | C3: Pavilion | D3: 176 | E3: Heron Properties | F3: Tacoma | G3: Been hearing bad things about Pavilion, south end job so competition will be cheap
A4: KOZ Lynnwood Apartments | B4: 44887 | C4: Kirtley-Cole | D4: 200 | E4: Koz | F4: Lynnwood | G4: Too busy to get around to, messy spec, and I imagine competition would be cheap. I found on mybuildingpermit.com that their plumbing budget is $4,220,000, which is $21,100 per unit
A5: 2501 Market Street | B5: 44894 | C5: Chinn | D5: 110 | E5: Jordan Selig Real Estate | F5: Ballard | G5: Typical Chinn asking for budgets. Job will rebid competitively in future.
A6: SRM Bellevue Way | B6: 44943 | C6: SRM | D6: 376 | E6: SRM | F6: Bellevue | G6: Very early budgeting. Will be asked to bid again in future. See notes in email I sent to myself.
A7: Apollo Apartments | B7: 44936 | C7: Exxel Pacific | D7: 255 | E7: Blackfish Capital | F7: Edmonds | G7: See email for explanation.
A8: Seatac Hyatt Hotel | B8: 44957 | C8: Chinn | D8: 198 | F8: Seatac | G8: See email for explanation.
A9: 3831 Stone Way | B9: 44965 | C9: Exxel Pacific | D9: 230 | E9: Prometheus Real Estate Group | F9: Wallingford | G9: Told Exxel Pacific that I would bid it if the senior PM called me. It's a schematic bid, and way too early, so this is probably just budget pricing. Exxel never called me. Jens said that Eric would call me, but he never did. Just going to wait until it's further along, i should get a bid invite later.
A10: Spruce Project | B10: 45071 | C10: Marpac | D10: 400 | E10: T Property Investments | F10: South seattle | G10: See email for explanation.
A11: St Lukes | B11: 45085 | C11: Venture | D11: 206 | E11: Security Properties | F11: Ballard | G11: See email for explanation.
A12: Ardea at Totem Lake | B12: 45100 | C12: Venture | D12: 170 | E12: TWG Development | F12: Totem Lake | G12: Venture project, busy with other bidding, Abossein design
A13: 1013 E Republican St | B13: 45121 | C13: Petra | D13: 75 | E13: Mike Martin? | F13: Capitol Hill | G13: Messy spec, Petra, probably a bunch of shitty plumbers bidding on it, etc
A14: Overlake Square | B14: 45120 | C14: Carmel Partners | D14: 569 | E14: Carmel Partners | F14: Redmond (Overlake) | G14: Too big. CP is big and there's a lot of risk here
A15: iVista Apartments | B15: 45133 | C15: Rush/Venture/Petra | D15: 256 | E15: Cosmos Group | F15: Lynnwood | G15: Don't have enough time before 2nd baby is due. Rush Commerical is GC. Nasty looking spec. Just got an invite to bid on Intracorp Lacey, so would like to concentrate on that. Also was invited to bid on this again in Feb/March 2024
A16: Modera Bridle Trails | B16: 45139 | C16: Mill Creek | D16: 372 | E16: Mill Creek | F16: Kirkland | G16: Atlas and JD bid it, so it's already going to be cheap. The Modera ID project was bid very cheaply, so they're going to have a very cheap expectation. Also, it's big and complicated, and I don't have time to deal with this bid. Have a baby coming in a week.
A17: 12th Place Apartments | B17: 45135 | C17: Compass | D17: 274 | E17: Gables Residential | F17: Bellevue | G17: Very messy fixture spec. Bid invite says there will be future rounds of bidding, so we will have another chance. I have a baby due in a week, and there are other projects to bid, so need to prioritize. Also, bid invite says the project won't go if it doesn't meet owners budget, so isn't very promising.
A18: Lacey Apartments | B18: 45134 | C18: Intracorp | D18: 216 | E18: Intracorp | F18: Lacey | G18: See email for explanation.
A19: AAA Management Renton | B19: 45163 | C19: Compass | D19: 343 | E19: AAA Management | F19: Renton | G19: AAA Management is shitty owner, requires a lot of time/effort. They wanted pricing on tear down, rebuild, and conversion from office to apartment. Too much time to think about. Too many other things to bid right now.
A20: Village at 47th | B20: 45187 | C20: ACG | D20: 272 | E20: Vintage Housing | F20: Tukwila | G20: Cannot find any info about permits online. Cannot figure out who bid it. Was a low level PE that called me about it, with little info. ACG is GC, which is probably a waste of time. Not sure if we want to work for them. There is other better stuff to bid on right now.
... A46: 185th Transit Center Apartments | B46: 45518 | C46: Redhawk | D46: 26 | E46: ? | F46: Shoreline | G46: Thought about doing this one, but I searched the lien records for Redhawk and it came up with several pages. Don't think it's worth even throwing my number out there.
A47: Sunrise 12 Apartments | B47: 45523 | C47: High Country | D47: 12 | F47: Shoreline | G47: Only 12 units, and I have plenty of other bids to concentrate on right now
A48: 165 Washington | B48: 45527 | C48: WG Clark | D48: 77 | E48: Johnson Carr | F48: Pioneer Square | G48: Feel like a project of this size is going to get a lot of bidders, and I've never been able to get a WG Clark job, so it's kind of pointless, and there's a ton of other jobs to bid on. Someone is going to come in stupid low.
A49: 149th Shoreline | B49: 45559 | C49: Rush | D49: 252 | E49: AAA Management | F49: Shoreline | G49: Job has been around for years, waste of time since it's AAA management and Rush. Lots to bid on, not going to waste my time on this one.
A50: Tacoma Holiday Inn Express | C50: Petra/Rmiller | D50: 127 | F50: Tacoma | G50: Too much to bid on right now, would require a lot of effort, and it's for GC's that I haven't worked for.
A51: Overlake Mixed Use | C51: WG Clark | D51: 233 | E51: Johnson Carr | F51: Overlake Redmond | G51: Too much to bid on right now, and didn't have time to get around to this one. Seems like Johnson Carr is struggling to get jobs going right now and I doubt this one is starting very soon.
A52: Uptown Apartments | B52: 45581 | C52: Compass | D52: 215 | E52: Kamiak | F52: Queen Anne | G52: Budgeting only. Kamiak can't get any jobs to start right now. Waste of time. If compass wants me to bid it, they'll call me.
A53: Bell 10 | B53: 45581 | C53: WG Clark | D53: 102 | E53: Guntower Capital | F53: Bellevue | G53: Alpine/Atlas has already done plumbing engineering, so they have a cheap price. Waste of time.
A54: 4742 Apartments | B54: 45636 | C54: WGClark, Rmiller, Chinn | D54: 89 | E54: Campus U Development | F54: U District | G54: Too much to bid right now, they have 3 GC's looking at it, seems like a waste of time.
A55: Astor Townhomes | B55: 45667 | C55: Fullwiler Construction | D55: 39 | E55: Fullwiler Construction, Shelter Homes? | F55: Roosevelt | G55: Never worked for these guys, seems like a messy job, townhomes, etc.
A56: Pixel Apartments | B56: 45665 | C56: Gencap | D56: 179 | E56: McCraken Properties | F56: Overlake Redmond | G56: Gencap is a waste of time, always gives their jobs to JD
A57: 12th & Olive | B57: 45671 | C57: Rush | D57: 134 | E57: Mack Real Estate (not the Mack that we've worked for before, this is a big one out of New York) | F57: Capitol Hill | G57: Wanted it back within a week. Seems unlikely to actually go because he's asking me for prices to add units, revise major parts of building. Rush uses super cheap numbers that I don't feel like working for.
A58: Acer House | B58: 45672 | C58: Rush | D58: 121 | E58: Great Expectations | F58: Central District | G58: Atlas has job. Trademark is bidding too. I bid on it the first time around, but it's very apparent that it's a waste of my time and is going to go for a stupid low number.
A59: 2nd & Bell | B59: 45674 | C59: Rush | D59: 175 | E59: HB Management / Paragon Real Estate | F59: Belltown | G59: Wolfe did design on job. Rush is used to stupid low numbers, and Trademark will probably be bidding. No point in wasting my time on this. Note that I bid this to Exxel I February 2021
A60: Tacoma Trax | B60: 45679 | C60: Gencap | D60: 202 | E60: Parkview Financial of Los Angeles (used to be a GIS International job) | F60: Tacoma | G60: Gencap is a waste of time. They are calling it "budgetary" pricing.
A61: Proctor 4 | B61: 45684 | C61: Rush | D61: 98 | E61: Rush | F61: Tacoma | G61: Rush is a waste of time. Going to be competing with Trademark and Atlas prices. They make you do finanical pre-quals and list your OH&P, etc.
A62: 124 Tacoma | B62: 45688 | C62: Rush | D62: 147 | E62: Rush | F62: Tacoma | G62: Rush is a waste of time. Going to be competing with Trademark and Atlas prices. They make you do finanical pre-quals and list your OH&P, etc.
A63: Milano Issaquah | B63: 45742 | C63: R Miller | D63: 65 | E63: Not sure | F63: Issaquah | G63: Too much to bid right now. Rush was looking at this a year ago. Doesn't seem like a good project.
... A79: Burl Apartments | B79: 46059 | C79: Compass | D79: 171 | E79: Spectrum | F79: Shoreline | G79: Was not able to get around to this bid because of hawaii trip and too busy. It had a lot of bidders on it including LJM, Wolfe, Atlas, Artemis and Western Mech, Trademark.
A80: 1661 East Olive Way | C80: Compass | G80: Too busy. Budget only at this time. Will probably be invited again.
A81: R22 Phase 1 and Phase 2 | B81: 46098 | C81: ACG | D81: =367+364 -> 731 | E81: ACG | F81: Redmond | G81: Too busy. Budget only at this time. Will probably be invited again.
A82: AMLI Spring District II | B82: 46088 | C82: Rafn | D82: 297 | E82: AMLI | F82: Bellevue | G82: Too busy, couldn't get around to it. Backlog is looking pretty good so starting to be selective.
